{
  "items": [
    {
      "type": "item",
      "title": "S01E01 - A Matter of Love",
      "link": "https://archive.org/download/Lucas-Tanner-1974-Series/Lucas%20Tanner%20%2823%20of%2023%29/S01E01%20-%20A%20Matter%20Of%20Love.ia.mp4",
      "thumbnail": "https://media.themoviedb.org/t/p/w500/ifbdm2EoqSEQxi5LXGV6dDA53fL.jpg",
      "fanart": "https://media.themoviedb.org/t/p/w1920_and_h800_multi_faces/b13AYZvbA5TzxpcZJPCA4J0BNyP.jpg",
      "summary": "A delicate problem for Lucas - try to cope with a bitter young girl who is falling in love with him.",
      "content": "episode",
      "tvshowtitle": "Lucas Tanner",
      "season": "1",
      "episode": "1",
      "year": "1974",
      "infolabels": {
        "title": "A Matter of Love",
        "tvshowtitle": "Lucas Tanner",
        "season": 1,
        "episode": 1,
        "plot": "A delicate problem for Lucas - try to cope with a bitter young girl who is falling in love with him.",
        "aired": "September 11, 1974",
        "mediatype": "episode"
      }
    },
    {
      "type": "item",
      "title": "S01E02 - Instant Replay",
      "link": "https://archive.org/download/Lucas-Tanner-1974-Series/Lucas%20Tanner%20%2823%20of%2023%29/S01E02%20-%20Instant%20Replay.ia.mp4",
      "thumbnail": "https://media.themoviedb.org/t/p/w500/ifbdm2EoqSEQxi5LXGV6dDA53fL.jpg",
      "fanart": "https://media.themoviedb.org/t/p/w1920_and_h800_multi_faces/b13AYZvbA5TzxpcZJPCA4J0BNyP.jpg",
      "summary": "We don't have an overview translated in English. Help us expand our database by adding one.",
      "content": "episode",
      "tvshowtitle": "Lucas Tanner",
      "season": "1",
      "episode": "2",
      "year": "1974",
      "infolabels": {
        "title": "Instant Replay",
        "tvshowtitle": "Lucas Tanner",
        "season": 1,
        "episode": 2,
        "plot": "We don't have an overview translated in English. Help us expand our database by adding one.",
        "aired": "September 18, 1974",
        "mediatype": "episode"
      }
    },
    {
      "type": "item",
      "title": "S01E03 - Thirteen Going on Twenty",
      "link": "https://archive.org/download/Lucas-Tanner-1974-Series/Lucas%20Tanner%20%2823%20of%2023%29/S01E03%20-%20Thirteen%20Going%20on%20Twenty.ia.mp4",
      "thumbnail": "https://media.themoviedb.org/t/p/w500/ifbdm2EoqSEQxi5LXGV6dDA53fL.jpg",
      "fanart": "https://media.themoviedb.org/t/p/w1920_and_h800_multi_faces/b13AYZvbA5TzxpcZJPCA4J0BNyP.jpg",
      "summary": "We don't have an overview translated in English. Help us expand our database by adding one.",
      "content": "episode",
      "tvshowtitle": "Lucas Tanner",
      "season": "1",
      "episode": "3",
      "year": "1974",
      "infolabels": {
        "title": "Thirteen Going on Twenty",
        "tvshowtitle": "Lucas Tanner",
        "season": 1,
        "episode": 3,
        "plot": "We don't have an overview translated in English. Help us expand our database by adding one.",
        "aired": "October 2, 1974",
        "mediatype": "episode"
      }
    },
    {
      "type": "item",
      "title": "S01E04 - Winners and Losers",
      "link": "https://archive.org/download/Lucas-Tanner-1974-Series/Lucas%20Tanner%20%2823%20of%2023%29/S01E04%20-%20Winners%20And%20Losers.ia.mp4",
      "thumbnail": "https://media.themoviedb.org/t/p/w500/ifbdm2EoqSEQxi5LXGV6dDA53fL.jpg",
      "fanart": "https://media.themoviedb.org/t/p/w1920_and_h800_multi_faces/b13AYZvbA5TzxpcZJPCA4J0BNyP.jpg",
      "summary": "We don't have an overview translated in English. Help us expand our database by adding one.",
      "content": "episode",
      "tvshowtitle": "Lucas Tanner",
      "season": "1",
      "episode": "4",
      "year": "1974",
      "infolabels": {
        "title": "Winners and Losers",
        "tvshowtitle": "Lucas Tanner",
        "season": 1,
        "episode": 4,
        "plot": "We don't have an overview translated in English. Help us expand our database by adding one.",
        "aired": "October 9, 1974",
        "mediatype": "episode"
      }
    },
    {
      "type": "item",
      "title": "S01E05 - A Question of Privacy",
      "link": "https://archive.org/download/Lucas-Tanner-1974-Series/Lucas%20Tanner%20%2823%20of%2023%29/S01E05%20-%20A%20Question%20Of%20Privacy.ia.mp4",
      "thumbnail": "https://media.themoviedb.org/t/p/w500/ifbdm2EoqSEQxi5LXGV6dDA53fL.jpg",
      "fanart": "https://media.themoviedb.org/t/p/w1920_and_h800_multi_faces/b13AYZvbA5TzxpcZJPCA4J0BNyP.jpg",
      "summary": "We don't have an overview translated in English. Help us expand our database by adding one.",
      "content": "episode",
      "tvshowtitle": "Lucas Tanner",
      "season": "1",
      "episode": "5",
      "year": "1974",
      "infolabels": {
        "title": "A Question of Privacy",
        "tvshowtitle": "Lucas Tanner",
        "season": 1,
        "episode": 5,
        "plot": "We don't have an overview translated in English. Help us expand our database by adding one.",
        "aired": "October 16, 1974",
        "mediatype": "episode"
      }
    },
    {
      "type": "item",
      "title": "S01E06 - Three Letter Word",
      "link": "https://archive.org/download/Lucas-Tanner-1974-Series/Lucas%20Tanner%20%2823%20of%2023%29/S01E06%20-%20Three%20Letter%20Word.ia.mp4",
      "thumbnail": "https://media.themoviedb.org/t/p/w500/ifbdm2EoqSEQxi5LXGV6dDA53fL.jpg",
      "fanart": "https://media.themoviedb.org/t/p/w1920_and_h800_multi_faces/b13AYZvbA5TzxpcZJPCA4J0BNyP.jpg",
      "summary": "We don't have an overview translated in English. Help us expand our database by adding one.",
      "content": "episode",
      "tvshowtitle": "Lucas Tanner",
      "season": "1",
      "episode": "6",
      "year": "1974",
      "infolabels": {
        "title": "Three Letter Word",
        "tvshowtitle": "Lucas Tanner",
        "season": 1,
        "episode": 6,
        "plot": "We don't have an overview translated in English. Help us expand our database by adding one.",
        "aired": "October 23, 1974",
        "mediatype": "episode"
      }
    },
    {
      "type": "item",
      "title": "S01E07 - By the Numbers",
      "link": "https://archive.org/download/Lucas-Tanner-1974-Series/Lucas%20Tanner%20%2823%20of%2023%29/S01E07%20-%20By%20The%20Numbers.ia.mp4",
      "thumbnail": "https://media.themoviedb.org/t/p/w500/ifbdm2EoqSEQxi5LXGV6dDA53fL.jpg",
      "fanart": "https://media.themoviedb.org/t/p/w1920_and_h800_multi_faces/b13AYZvbA5TzxpcZJPCA4J0BNyP.jpg",
      "summary": "We don't have an overview translated in English. Help us expand our database by adding one.",
      "content": "episode",
      "tvshowtitle": "Lucas Tanner",
      "season": "1",
      "episode": "7",
      "year": "1974",
      "infolabels": {
        "title": "By the Numbers",
        "tvshowtitle": "Lucas Tanner",
        "season": 1,
        "episode": 7,
        "plot": "We don't have an overview translated in English. Help us expand our database by adding one.",
        "aired": "November 6, 1974",
        "mediatype": "episode"
      }
    },
    {
      "type": "item",
      "title": "S01E08 - Echoes",
      "link": "https://archive.org/download/Lucas-Tanner-1974-Series/Lucas%20Tanner%20%2823%20of%2023%29/S01E08%20-%20Echos.ia.mp4",
      "thumbnail": "https://media.themoviedb.org/t/p/w500/ifbdm2EoqSEQxi5LXGV6dDA53fL.jpg",
      "fanart": "https://media.themoviedb.org/t/p/w1920_and_h800_multi_faces/b13AYZvbA5TzxpcZJPCA4J0BNyP.jpg",
      "summary": "We don't have an overview translated in English. Help us expand our database by adding one.",
      "content": "episode",
      "tvshowtitle": "Lucas Tanner",
      "season": "1",
      "episode": "8",
      "year": "1974",
      "infolabels": {
        "title": "Echoes",
        "tvshowtitle": "Lucas Tanner",
        "season": 1,
        "episode": 8,
        "plot": "We don't have an overview translated in English. Help us expand our database by adding one.",
        "aired": "November 13, 1974",
        "mediatype": "episode"
      }
    },
    {
      "type": "item",
      "title": "S01E09 - Look the Other Way",
      "link": "https://archive.org/download/Lucas-Tanner-1974-Series/Lucas%20Tanner%20%2823%20of%2023%29/S01E09%20-%20Look%20the%20Other%20Way.ia.mp4",
      "thumbnail": "https://media.themoviedb.org/t/p/w500/ifbdm2EoqSEQxi5LXGV6dDA53fL.jpg",
      "fanart": "https://media.themoviedb.org/t/p/w1920_and_h800_multi_faces/b13AYZvbA5TzxpcZJPCA4J0BNyP.jpg",
      "summary": "We don't have an overview translated in English. Help us expand our database by adding one.",
      "content": "episode",
      "tvshowtitle": "Lucas Tanner",
      "season": "1",
      "episode": "9",
      "year": "1974",
      "infolabels": {
        "title": "Look the Other Way",
        "tvshowtitle": "Lucas Tanner",
        "season": 1,
        "episode": 9,
        "plot": "We don't have an overview translated in English. Help us expand our database by adding one.",
        "aired": "November 20, 1974",
        "mediatype": "episode"
      }
    },
    {
      "type": "item",
      "title": "S01E10 - Cheers",
      "link": "https://archive.org/download/Lucas-Tanner-1974-Series/Lucas%20Tanner%20%2823%20of%2023%29/S01E10%20-%20Cheers.ia.mp4",
      "thumbnail": "https://media.themoviedb.org/t/p/w500/ifbdm2EoqSEQxi5LXGV6dDA53fL.jpg",
      "fanart": "https://media.themoviedb.org/t/p/w1920_and_h800_multi_faces/b13AYZvbA5TzxpcZJPCA4J0BNyP.jpg",
      "summary": "We don't have an overview translated in English. Help us expand our database by adding one.",
      "content": "episode",
      "tvshowtitle": "Lucas Tanner",
      "season": "1",
      "episode": "10",
      "year": "1974",
      "infolabels": {
        "title": "Cheers",
        "tvshowtitle": "Lucas Tanner",
        "season": 1,
        "episode": 10,
        "plot": "We don't have an overview translated in English. Help us expand our database by adding one.",
        "aired": "December 4, 1974",
        "mediatype": "episode"
      }
    },
    {
      "type": "item",
      "title": "S01E11 - Merry Gentlemen",
      "link": "https://archive.org/download/Lucas-Tanner-1974-Series/Lucas%20Tanner%20%2823%20of%2023%29/S01E11%20-%20Merry%20Gentlemen.ia.mp4",
      "thumbnail": "https://media.themoviedb.org/t/p/w500/ifbdm2EoqSEQxi5LXGV6dDA53fL.jpg",
      "fanart": "https://media.themoviedb.org/t/p/w1920_and_h800_multi_faces/b13AYZvbA5TzxpcZJPCA4J0BNyP.jpg",
      "summary": "We don't have an overview translated in English. Help us expand our database by adding one.",
      "content": "episode",
      "tvshowtitle": "Lucas Tanner",
      "season": "1",
      "episode": "11",
      "year": "1974",
      "infolabels": {
        "title": "Merry Gentlemen",
        "tvshowtitle": "Lucas Tanner",
        "season": 1,
        "episode": 11,
        "plot": "We don't have an overview translated in English. Help us expand our database by adding one.",
        "aired": "December 25, 1974",
        "mediatype": "episode"
      }
    },
    {
      "type": "item",
      "title": "S01E12 - Bonus Baby",
      "link": "https://archive.org/download/Lucas-Tanner-1974-Series/Lucas%20Tanner%20%2823%20of%2023%29/S01E12%20-%20The%20Bonus%20Baby.ia.mp4",
      "thumbnail": "https://media.themoviedb.org/t/p/w500/ifbdm2EoqSEQxi5LXGV6dDA53fL.jpg",
      "fanart": "https://media.themoviedb.org/t/p/w1920_and_h800_multi_faces/b13AYZvbA5TzxpcZJPCA4J0BNyP.jpg",
      "summary": "We don't have an overview translated in English. Help us expand our database by adding one.",
      "content": "episode",
      "tvshowtitle": "Lucas Tanner",
      "season": "1",
      "episode": "12",
      "year": "1975",
      "infolabels": {
        "title": "Bonus Baby",
        "tvshowtitle": "Lucas Tanner",
        "season": 1,
        "episode": 12,
        "plot": "We don't have an overview translated in English. Help us expand our database by adding one.",
        "aired": "January 8, 1975",
        "mediatype": "episode"
      }
    },
    {
      "type": "item",
      "title": "S01E13 - Pay the Two Dollars",
      "link": "https://archive.org/download/Lucas-Tanner-1974-Series/Lucas%20Tanner%20%2823%20of%2023%29/S01E13%20-%20Pay%20the%20Two%20Dollars.ia.mp4",
      "thumbnail": "https://media.themoviedb.org/t/p/w500/ifbdm2EoqSEQxi5LXGV6dDA53fL.jpg",
      "fanart": "https://media.themoviedb.org/t/p/w1920_and_h800_multi_faces/b13AYZvbA5TzxpcZJPCA4J0BNyP.jpg",
      "summary": "We don't have an overview translated in English. Help us expand our database by adding one.",
      "content": "episode",
      "tvshowtitle": "Lucas Tanner",
      "season": "1",
      "episode": "13",
      "year": "1975",
      "infolabels": {
        "title": "Pay the Two Dollars",
        "tvshowtitle": "Lucas Tanner",
        "season": 1,
        "episode": 13,
        "plot": "We don't have an overview translated in English. Help us expand our database by adding one.",
        "aired": "January 15, 1975",
        "mediatype": "episode"
      }
    },
    {
      "type": "item",
      "title": "S01E14 - Those Who Cannot Count, Teach",
      "link": "https://archive.org/download/Lucas-Tanner-1974-Series/Lucas%20Tanner%20%2823%20of%2023%29/S01E14%20-%20Those%20Who%20Cannot%2C%20Teach.ia.mp4",
      "thumbnail": "https://media.themoviedb.org/t/p/w500/ifbdm2EoqSEQxi5LXGV6dDA53fL.jpg",
      "fanart": "https://media.themoviedb.org/t/p/w1920_and_h800_multi_faces/b13AYZvbA5TzxpcZJPCA4J0BNyP.jpg",
      "summary": "We don't have an overview translated in English. Help us expand our database by adding one.",
      "content": "episode",
      "tvshowtitle": "Lucas Tanner",
      "season": "1",
      "episode": "14",
      "year": "1975",
      "infolabels": {
        "title": "Those Who Cannot Count, Teach",
        "tvshowtitle": "Lucas Tanner",
        "season": 1,
        "episode": 14,
        "plot": "We don't have an overview translated in English. Help us expand our database by adding one.",
        "aired": "January 22, 1975",
        "mediatype": "episode"
      }
    },
    {
      "type": "item",
      "title": "S01E15 - What's Wrong with Bobby?",
      "link": "https://archive.org/download/Lucas-Tanner-1974-Series/Lucas%20Tanner%20%2823%20of%2023%29/S01E15%20-%20What%27s%20Wrong%20With%20Bobbie.ia.mp4",
      "thumbnail": "https://media.themoviedb.org/t/p/w500/ifbdm2EoqSEQxi5LXGV6dDA53fL.jpg",
      "fanart": "https://media.themoviedb.org/t/p/w1920_and_h800_multi_faces/b13AYZvbA5TzxpcZJPCA4J0BNyP.jpg",
      "summary": "We don't have an overview translated in English. Help us expand our database by adding one.",
      "content": "episode",
      "tvshowtitle": "Lucas Tanner",
      "season": "1",
      "episode": "15",
      "year": "1975",
      "infolabels": {
        "title": "What's Wrong with Bobby?",
        "tvshowtitle": "Lucas Tanner",
        "season": 1,
        "episode": 15,
        "plot": "We don't have an overview translated in English. Help us expand our database by adding one.",
        "aired": "January 29, 1975",
        "mediatype": "episode"
      }
    },
    {
      "type": "item",
      "title": "S01E16 - Collision",
      "link": "https://archive.org/download/Lucas-Tanner-1974-Series/Lucas%20Tanner%20%2823%20of%2023%29/S01E16%20-%20Collision.ia.mp4",
      "thumbnail": "https://media.themoviedb.org/t/p/w500/ifbdm2EoqSEQxi5LXGV6dDA53fL.jpg",
      "fanart": "https://media.themoviedb.org/t/p/w1920_and_h800_multi_faces/b13AYZvbA5TzxpcZJPCA4J0BNyP.jpg",
      "summary": "We don't have an overview translated in English. Help us expand our database by adding one.",
      "content": "episode",
      "tvshowtitle": "Lucas Tanner",
      "season": "1",
      "episode": "16",
      "year": "1975",
      "infolabels": {
        "title": "Collision",
        "tvshowtitle": "Lucas Tanner",
        "season": 1,
        "episode": 16,
        "plot": "We don't have an overview translated in English. Help us expand our database by adding one.",
        "aired": "February 5, 1975",
        "mediatype": "episode"
      }
    },
    {
      "type": "item",
      "title": "S01E17 - Why Not a Happy Ending?",
      "link": "https://archive.org/download/Lucas-Tanner-1974-Series/Lucas%20Tanner%20%2823%20of%2023%29/S01E17%20-%20Why%20Not%20a%20Happy%20Ending.ia.mp4",
      "thumbnail": "https://media.themoviedb.org/t/p/w500/ifbdm2EoqSEQxi5LXGV6dDA53fL.jpg",
      "fanart": "https://media.themoviedb.org/t/p/w1920_and_h800_multi_faces/b13AYZvbA5TzxpcZJPCA4J0BNyP.jpg",
      "summary": "We don't have an overview translated in English. Help us expand our database by adding one.",
      "content": "episode",
      "tvshowtitle": "Lucas Tanner",
      "season": "1",
      "episode": "17",
      "year": "1975",
      "infolabels": {
        "title": "Why Not a Happy Ending?",
        "tvshowtitle": "Lucas Tanner",
        "season": 1,
        "episode": 17,
        "plot": "We don't have an overview translated in English. Help us expand our database by adding one.",
        "aired": "February 12, 1975",
        "mediatype": "episode"
      }
    },
    {
      "type": "item",
      "title": "S01E18 - Shattered",
      "link": "https://archive.org/download/Lucas-Tanner-1974-Series/Lucas%20Tanner%20%2823%20of%2023%29/S01E18%20-%20Shattered.ia.mp4",
      "thumbnail": "https://media.themoviedb.org/t/p/w500/ifbdm2EoqSEQxi5LXGV6dDA53fL.jpg",
      "fanart": "https://media.themoviedb.org/t/p/w1920_and_h800_multi_faces/b13AYZvbA5TzxpcZJPCA4J0BNyP.jpg",
      "summary": "We don't have an overview translated in English. Help us expand our database by adding one.",
      "content": "episode",
      "tvshowtitle": "Lucas Tanner",
      "season": "1",
      "episode": "18",
      "year": "1975",
      "infolabels": {
        "title": "Shattered",
        "tvshowtitle": "Lucas Tanner",
        "season": 1,
        "episode": 18,
        "plot": "We don't have an overview translated in English. Help us expand our database by adding one.",
        "aired": "February 19, 1975",
        "mediatype": "episode"
      }
    },
    {
      "type": "item",
      "title": "S01E19 - The Noise of a Quiet Weekend",
      "link": "https://archive.org/download/Lucas-Tanner-1974-Series/Lucas%20Tanner%20%2823%20of%2023%29/S01E19%20-%20The%20Noise%20of%20a%20Quiet%20Weekend.ia.mp4",
      "thumbnail": "https://media.themoviedb.org/t/p/w500/ifbdm2EoqSEQxi5LXGV6dDA53fL.jpg",
      "fanart": "https://media.themoviedb.org/t/p/w1920_and_h800_multi_faces/b13AYZvbA5TzxpcZJPCA4J0BNyP.jpg",
      "summary": "We don't have an overview translated in English. Help us expand our database by adding one.",
      "content": "episode",
      "tvshowtitle": "Lucas Tanner",
      "season": "1",
      "episode": "19",
      "year": "1975",
      "infolabels": {
        "title": "The Noise of a Quiet Weekend",
        "tvshowtitle": "Lucas Tanner",
        "season": 1,
        "episode": 19,
        "plot": "We don't have an overview translated in English. Help us expand our database by adding one.",
        "aired": "February 26, 1975",
        "mediatype": "episode"
      }
    },
    {
      "type": "item",
      "title": "S01E20 - Requiem for a Son",
      "link": "https://archive.org/download/Lucas-Tanner-1974-Series/Lucas%20Tanner%20%2823%20of%2023%29/S01E20%20-%20Requiem%20For%20a%20Son.ia.mp4",
      "thumbnail": "https://media.themoviedb.org/t/p/w500/ifbdm2EoqSEQxi5LXGV6dDA53fL.jpg",
      "fanart": "https://media.themoviedb.org/t/p/w1920_and_h800_multi_faces/b13AYZvbA5TzxpcZJPCA4J0BNyP.jpg",
      "summary": "We don't have an overview translated in English. Help us expand our database by adding one.",
      "content": "episode",
      "tvshowtitle": "Lucas Tanner",
      "season": "1",
      "episode": "20",
      "year": "1975",
      "infolabels": {
        "title": "Requiem for a Son",
        "tvshowtitle": "Lucas Tanner",
        "season": 1,
        "episode": 20,
        "plot": "We don't have an overview translated in English. Help us expand our database by adding one.",
        "aired": "March 12, 1975",
        "mediatype": "episode"
      }
    },
    {
      "type": "item",
      "title": "S01E21 - A Touch of Bribery",
      "link": "https://archive.org/download/Lucas-Tanner-1974-Series/Lucas%20Tanner%20%2823%20of%2023%29/S01E21%20-%20A%20Touch%20of%20Bribery.ia.mp4",
      "thumbnail": "https://media.themoviedb.org/t/p/w500/ifbdm2EoqSEQxi5LXGV6dDA53fL.jpg",
      "fanart": "https://media.themoviedb.org/t/p/w1920_and_h800_multi_faces/b13AYZvbA5TzxpcZJPCA4J0BNyP.jpg",
      "summary": "We don't have an overview translated in English. Help us expand our database by adding one.",
      "content": "episode",
      "tvshowtitle": "Lucas Tanner",
      "season": "1",
      "episode": "21",
      "year": "1975",
      "infolabels": {
        "title": "A Touch of Bribery",
        "tvshowtitle": "Lucas Tanner",
        "season": 1,
        "episode": 21,
        "plot": "We don't have an overview translated in English. Help us expand our database by adding one.",
        "aired": "April 2, 1975",
        "mediatype": "episode"
      }
    },
    {
      "type": "item",
      "title": "S01E22 - One to One",
      "link": "https://archive.org/download/Lucas-Tanner-1974-Series/Lucas%20Tanner%20%2823%20of%2023%29/S01E22%20-%20One%20To%20One.ia.mp4",
      "thumbnail": "https://media.themoviedb.org/t/p/w500/ifbdm2EoqSEQxi5LXGV6dDA53fL.jpg",
      "fanart": "https://media.themoviedb.org/t/p/w1920_and_h800_multi_faces/b13AYZvbA5TzxpcZJPCA4J0BNyP.jpg",
      "summary": "We don't have an overview translated in English. Help us expand our database by adding one.",
      "content": "episode",
      "tvshowtitle": "Lucas Tanner",
      "season": "1",
      "episode": "22",
      "year": "1975",
      "infolabels": {
        "title": "One to One",
        "tvshowtitle": "Lucas Tanner",
        "season": 1,
        "episode": 22,
        "plot": "We don't have an overview translated in English. Help us expand our database by adding one.",
        "aired": "April 9, 1975",
        "mediatype": "episode"
      }
    }
  ]
}