{
  "items": [
    {
      "type": "item",
      "title": "S01E01 - The Twisted Image",
      "link": "https://archive.org/download/s-01-e-26-papa-benjamin/Thriller%20%281960%29%20-%20COMPLETE/S01E01%20-%20THE%20TWISTED%20IMAGE.ia.mp4",
      "thumbnail": "https://media.themoviedb.org/t/p/w227_and_h127_face/vmm1cHL0qBiXuB81FCuy68KMG2P.jpg",
      "fanart": "https://media.themoviedb.org/t/p/w1920_and_h800_multi_faces/4gFB4BF4zojCrD5JVHp74xWcoQL.jpg",
      "summary": "When the paths of a disturbed young man (consumed with the idea of taking over the life of his boss) and a disturbed young woman (obsessed with the same man) cross, the results are disatrous.",
      "content": "episode",
      "tvshowtitle": "Thriller",
      "season": "1",
      "episode": "1",
      "year": "1960",
      "infolabels": {
        "title": "The Twisted Image",
        "tvshowtitle": "Thriller",
        "season": 1,
        "episode": 1,
        "plot": "When the paths of a disturbed young man (consumed with the idea of taking over the life of his boss) and a disturbed young woman (obsessed with the same man) cross, the results are disatrous.",
        "aired": "September 13, 1960",
        "mediatype": "episode"
      }
    },
    {
      "type": "item",
      "title": "S01E02 - Child's Play",
      "link": "https://archive.org/download/s-01-e-26-papa-benjamin/Thriller%20%281960%29%20-%20COMPLETE/S01E02%20-%20CHILD%27S%20PLAY.ia.mp4",
      "thumbnail": "https://media.themoviedb.org/t/p/w227_and_h127_face/rPIu4fFamice12CTArSQkwQ5KhT.jpg",
      "fanart": "https://media.themoviedb.org/t/p/w1920_and_h800_multi_faces/4gFB4BF4zojCrD5JVHp74xWcoQL.jpg",
      "summary": "A young boy with an unhappy homelife gets dangerously absorbed in his imagination.",
      "content": "episode",
      "tvshowtitle": "Thriller",
      "season": "1",
      "episode": "2",
      "year": "1960",
      "infolabels": {
        "title": "Child's Play",
        "tvshowtitle": "Thriller",
        "season": 1,
        "episode": 2,
        "plot": "A young boy with an unhappy homelife gets dangerously absorbed in his imagination.",
        "aired": "September 20, 1960",
        "mediatype": "episode"
      }
    },
    {
      "type": "item",
      "title": "S01E03 - Worse Than Murder",
      "link": "https://archive.org/download/s-01-e-26-papa-benjamin/Thriller%20%281960%29%20-%20COMPLETE/S01E03%20-%20WORSE%20THAN%20MURDER.ia.mp4",
      "thumbnail": "https://media.themoviedb.org/t/p/w227_and_h127_face/row8x2qeioKqGOJytKY8wLCOoM5.jpg",
      "fanart": "https://media.themoviedb.org/t/p/w1920_and_h800_multi_faces/4gFB4BF4zojCrD5JVHp74xWcoQL.jpg",
      "summary": "A man dies and leaves a diary describing how he and his sister murdered a woman. The sister's unscrupulous daughter-in-law uses the diary for blackmail.",
      "content": "episode",
      "tvshowtitle": "Thriller",
      "season": "1",
      "episode": "3",
      "year": "1960",
      "infolabels": {
        "title": "Worse Than Murder",
        "tvshowtitle": "Thriller",
        "season": 1,
        "episode": 3,
        "plot": "A man dies and leaves a diary describing how he and his sister murdered a woman. The sister's unscrupulous daughter-in-law uses the diary for blackmail.",
        "aired": "September 27, 1960",
        "mediatype": "episode"
      }
    },
    {
      "type": "item",
      "title": "S01E04 - The Mark of the Hand",
      "link": "https://archive.org/download/s-01-e-26-papa-benjamin/Thriller%20%281960%29%20-%20COMPLETE/S01E04%20-%20THE%20MARK%20OF%20THE%20HAND.ia.mp4",
      "thumbnail": "https://media.themoviedb.org/t/p/w227_and_h127_face/nZ0dvhaFpn8xvpe7uJyPsGob7ku.jpg",
      "fanart": "https://media.themoviedb.org/t/p/w1920_and_h800_multi_faces/4gFB4BF4zojCrD5JVHp74xWcoQL.jpg",
      "summary": "An eight-year-old girl is accused of murdering a man and then trying to kill again.",
      "content": "episode",
      "tvshowtitle": "Thriller",
      "season": "1",
      "episode": "4",
      "year": "1960",
      "infolabels": {
        "title": "The Mark of the Hand",
        "tvshowtitle": "Thriller",
        "season": 1,
        "episode": 4,
        "plot": "An eight-year-old girl is accused of murdering a man and then trying to kill again.",
        "aired": "October 4, 1960",
        "mediatype": "episode"
      }
    },
    {
      "type": "item",
      "title": "S01E05 - Rose's Last Summer",
      "link": "https://archive.org/download/s-01-e-26-papa-benjamin/Thriller%20%281960%29%20-%20COMPLETE/S01E05%20-%20ROSE%27S%20LAST%20SUMMER.ia.mp4",
      "thumbnail": "https://media.themoviedb.org/t/p/w227_and_h127_face/d7cHdljV3CYbuZaYcrRFS6LKhsp.jpg",
      "fanart": "https://media.themoviedb.org/t/p/w1920_and_h800_multi_faces/4gFB4BF4zojCrD5JVHp74xWcoQL.jpg",
      "summary": "When an aging film actress dies under mysterious circumstances a friend and her former husband try to find out what happened to her.",
      "content": "episode",
      "tvshowtitle": "Thriller",
      "season": "1",
      "episode": "5",
      "year": "1960",
      "infolabels": {
        "title": "Rose's Last Summer",
        "tvshowtitle": "Thriller",
        "season": 1,
        "episode": 5,
        "plot": "When an aging film actress dies under mysterious circumstances a friend and her former husband try to find out what happened to her.",
        "aired": "October 11, 1960",
        "mediatype": "episode"
      }
    },
    {
      "type": "item",
      "title": "S01E06 - The Guilty Men",
      "link": "https://archive.org/download/s-01-e-26-papa-benjamin/Thriller%20%281960%29%20-%20COMPLETE/S01E06%20-%20THE%20GUILTY%20MEN.ia.mp4",
      "thumbnail": "https://media.themoviedb.org/t/p/w227_and_h127_face/t1mcUsefi7kYICkGcNZJnCCNwSO.jpg",
      "fanart": "https://media.themoviedb.org/t/p/w1920_and_h800_multi_faces/4gFB4BF4zojCrD5JVHp74xWcoQL.jpg",
      "summary": "The inner workings of a crime syndicate are examined as their mouthpiece lawyer wrestles with his conscience over the future of the organization.",
      "content": "episode",
      "tvshowtitle": "Thriller",
      "season": "1",
      "episode": "6",
      "year": "1960",
      "infolabels": {
        "title": "The Guilty Men",
        "tvshowtitle": "Thriller",
        "season": 1,
        "episode": 6,
        "plot": "The inner workings of a crime syndicate are examined as their mouthpiece lawyer wrestles with his conscience over the future of the organization.",
        "aired": "October 18, 1960",
        "mediatype": "episode"
      }
    },
    {
      "type": "item",
      "title": "S01E07 - The Purple Room",
      "link": "https://archive.org/download/s-01-e-26-papa-benjamin/Thriller%20%281960%29%20-%20COMPLETE/S01E07%20-%20THE%20PURPLE%20ROOM.ia.mp4",
      "thumbnail": "https://media.themoviedb.org/t/p/w227_and_h127_face/k6KffbSHMKaUtKlvkXf5RYn05Y4.jpg",
      "fanart": "https://media.themoviedb.org/t/p/w1920_and_h800_multi_faces/4gFB4BF4zojCrD5JVHp74xWcoQL.jpg",
      "summary": "A man who inherits a house from his brother has one night to decide whether or not to stay - if he leaves, his cousins will inherit the house instead. He expects his cousins to try and frighten him into leaving, but could the strange happenings be more than pranks?",
      "content": "episode",
      "tvshowtitle": "Thriller",
      "season": "1",
      "episode": "7",
      "year": "1960",
      "infolabels": {
        "title": "The Purple Room",
        "tvshowtitle": "Thriller",
        "season": 1,
        "episode": 7,
        "plot": "A man who inherits a house from his brother has one night to decide whether or not to stay - if he leaves, his cousins will inherit the house instead. He expects his cousins to try and frighten him into leaving, but could the strange happenings be more than pranks?",
        "aired": "October 25, 1960",
        "mediatype": "episode"
      }
    },
    {
      "type": "item",
      "title": "S01E08 - The Watcher",
      "link": "https://archive.org/download/s-01-e-26-papa-benjamin/Thriller%20%281960%29%20-%20COMPLETE/S01E08%20-%20THE%20WATCHER.ia.mp4",
      "thumbnail": "https://media.themoviedb.org/t/p/w227_and_h127_face/movkNhTS44zxFlfAhqXdIOvbg1t.jpg",
      "fanart": "https://media.themoviedb.org/t/p/w1920_and_h800_multi_faces/4gFB4BF4zojCrD5JVHp74xWcoQL.jpg",
      "summary": "A twisted zealot seeks to kill all those he feels are sinners.",
      "content": "episode",
      "tvshowtitle": "Thriller",
      "season": "1",
      "episode": "8",
      "year": "1960",
      "infolabels": {
        "title": "The Watcher",
        "tvshowtitle": "Thriller",
        "season": 1,
        "episode": 8,
        "plot": "A twisted zealot seeks to kill all those he feels are sinners.",
        "aired": "November 1, 1960",
        "mediatype": "episode"
      }
    },
    {
      "type": "item",
      "title": "S01E09 - Girl With a Secret",
      "link": "https://archive.org/download/s-01-e-26-papa-benjamin/Thriller%20%281960%29%20-%20COMPLETE/S01E09%20-%20GIRL%20WITH%20A%20SECRET.ia.mp4",
      "thumbnail": "https://media.themoviedb.org/t/p/w227_and_h127_face/uvr8R6DsfoOTmGQmyynGBJT8OOV.jpg",
      "fanart": "https://media.themoviedb.org/t/p/w1920_and_h800_multi_faces/4gFB4BF4zojCrD5JVHp74xWcoQL.jpg",
      "summary": "When the wife of a government agent inadvertently discovers the details of one of his missions she becomes a girl with a secret that must be kept at all costs.",
      "content": "episode",
      "tvshowtitle": "Thriller",
      "season": "1",
      "episode": "9",
      "year": "1960",
      "infolabels": {
        "title": "Girl With a Secret",
        "tvshowtitle": "Thriller",
        "season": 1,
        "episode": 9,
        "plot": "When the wife of a government agent inadvertently discovers the details of one of his missions she becomes a girl with a secret that must be kept at all costs.",
        "aired": "November 15, 1960",
        "mediatype": "episode"
      }
    },
    {
      "type": "item",
      "title": "S01E10 - The Prediction",
      "link": "https://archive.org/download/s-01-e-26-papa-benjamin/Thriller%20%281960%29%20-%20COMPLETE/S01E10%20-%20THE%20PREDICTION.ia.mp4",
      "thumbnail": "https://media.themoviedb.org/t/p/w227_and_h127_face/vdKbgyyYjxMgbJKYdXKwvQFEzWI.jpg",
      "fanart": "https://media.themoviedb.org/t/p/w1920_and_h800_multi_faces/4gFB4BF4zojCrD5JVHp74xWcoQL.jpg",
      "summary": "A phony clairvoyant suddenly starts having genuine premonitions. Will he be able to save those closest to him when he sees death in their future?",
      "content": "episode",
      "tvshowtitle": "Thriller",
      "season": "1",
      "episode": "10",
      "year": "1960",
      "infolabels": {
        "title": "The Prediction",
        "tvshowtitle": "Thriller",
        "season": 1,
        "episode": 10,
        "plot": "A phony clairvoyant suddenly starts having genuine premonitions. Will he be able to save those closest to him when he sees death in their future?",
        "aired": "November 22, 1960",
        "mediatype": "episode"
      }
    },
    {
      "type": "item",
      "title": "S01E11 - The Fatal Impulse",
      "link": "https://archive.org/download/s-01-e-26-papa-benjamin/Thriller%20%281960%29%20-%20COMPLETE/S01E11%20-%20THE%20FATAL%20IMPULSE.ia.mp4",
      "thumbnail": "https://media.themoviedb.org/t/p/w227_and_h127_face/dbDGj3deyiBXQNQiAXWVBBxW164.jpg",
      "fanart": "https://media.themoviedb.org/t/p/w1920_and_h800_multi_faces/4gFB4BF4zojCrD5JVHp74xWcoQL.jpg",
      "summary": "A canidate for Mayor is told he won't live through the next day. The police are sent to protect him and we follow their actions as well as those of the potential killer.",
      "content": "episode",
      "tvshowtitle": "Thriller",
      "season": "1",
      "episode": "11",
      "year": "1960",
      "infolabels": {
        "title": "The Fatal Impulse",
        "tvshowtitle": "Thriller",
        "season": 1,
        "episode": 11,
        "plot": "A canidate for Mayor is told he won't live through the next day. The police are sent to protect him and we follow their actions as well as those of the potential killer.",
        "aired": "November 29, 1960",
        "mediatype": "episode"
      }
    },
    {
      "type": "item",
      "title": "S01E12 - The Big Blackout",
      "link": "https://archive.org/download/s-01-e-26-papa-benjamin/Thriller%20%281960%29%20-%20COMPLETE/S01E12%20-%20THE%20BIG%20BLACKOUT.ia.mp4",
      "thumbnail": "https://media.themoviedb.org/t/p/w227_and_h127_face/9VKBvjPVtuAKk2IQf98VdtV9Pmf.jpg",
      "fanart": "https://media.themoviedb.org/t/p/w1920_and_h800_multi_faces/4gFB4BF4zojCrD5JVHp74xWcoQL.jpg",
      "summary": "A former alcoholic is haunted by a past he can't remember. Will he be able to stay alive long enough to unravel the mystery?",
      "content": "episode",
      "tvshowtitle": "Thriller",
      "season": "1",
      "episode": "12",
      "year": "1960",
      "infolabels": {
        "title": "The Big Blackout",
        "tvshowtitle": "Thriller",
        "season": 1,
        "episode": 12,
        "plot": "A former alcoholic is haunted by a past he can't remember. Will he be able to stay alive long enough to unravel the mystery?",
        "aired": "December 6, 1960",
        "mediatype": "episode"
      }
    },
    {
      "type": "item",
      "title": "S01E13 - Knock Three-One-Two",
      "link": "https://archive.org/download/s-01-e-26-papa-benjamin/Thriller%20%281960%29%20-%20COMPLETE/S01E13%20-%20KNOCK%20THREE-ONE-TWO.ia.mp4",
      "thumbnail": "https://media.themoviedb.org/t/p/w227_and_h127_face/jUwMdKqgq2ZTY8wCjbTmtbbHxC7.jpg",
      "fanart": "https://media.themoviedb.org/t/p/w1920_and_h800_multi_faces/4gFB4BF4zojCrD5JVHp74xWcoQL.jpg",
      "summary": "A man desparate for money decides to enlist the help of a serial killer in getting the cash he needs from his wife.",
      "content": "episode",
      "tvshowtitle": "Thriller",
      "season": "1",
      "episode": "13",
      "year": "1960",
      "infolabels": {
        "title": "Knock Three-One-Two",
        "tvshowtitle": "Thriller",
        "season": 1,
        "episode": 13,
        "plot": "A man desparate for money decides to enlist the help of a serial killer in getting the cash he needs from his wife.",
        "aired": "December 13, 1960",
        "mediatype": "episode"
      }
    },
    {
      "type": "item",
      "title": "S01E14 - Man in the Middle",
      "link": "https://archive.org/download/s-01-e-26-papa-benjamin/Thriller%20%281960%29%20-%20COMPLETE/S01E14%20-%20MAN%20IN%20THE%20MIDDLE.ia.mp4",
      "thumbnail": "https://media.themoviedb.org/t/p/w227_and_h127_face/k46a6UX8D4UjMAnEkOTx6MZleDK.jpg",
      "fanart": "https://media.themoviedb.org/t/p/w1920_and_h800_multi_faces/4gFB4BF4zojCrD5JVHp74xWcoQL.jpg",
      "summary": "A man overhears the kidnapping and murder plot of two unsavory characters and tries to prevent it from being carried out despite the fact that his own life is in danger.",
      "content": "episode",
      "tvshowtitle": "Thriller",
      "season": "1",
      "episode": "14",
      "year": "1960",
      "infolabels": {
        "title": "Man in the Middle",
        "tvshowtitle": "Thriller",
        "season": 1,
        "episode": 14,
        "plot": "A man overhears the kidnapping and murder plot of two unsavory characters and tries to prevent it from being carried out despite the fact that his own life is in danger.",
        "aired": "December 20, 1960",
        "mediatype": "episode"
      }
    },
    {
      "type": "item",
      "title": "S01E15 - The Cheaters",
      "link": "https://archive.org/download/s-01-e-26-papa-benjamin/Thriller%20%281960%29%20-%20COMPLETE/S01E15%20-%20THE%20CHEATERS.ia.mp4",
      "thumbnail": "https://media.themoviedb.org/t/p/w227_and_h127_face/5KcunpNq9l1ekBfPnko5D4Ayejv.jpg",
      "fanart": "https://media.themoviedb.org/t/p/w1920_and_h800_multi_faces/4gFB4BF4zojCrD5JVHp74xWcoQL.jpg",
      "summary": "A pair of very unusual glasses allow the wearer to see the absolute truth about whatever they look upon. We see what happens as they pass from one owner to another.",
      "content": "episode",
      "tvshowtitle": "Thriller",
      "season": "1",
      "episode": "15",
      "year": "1960",
      "infolabels": {
        "title": "The Cheaters",
        "tvshowtitle": "Thriller",
        "season": 1,
        "episode": 15,
        "plot": "A pair of very unusual glasses allow the wearer to see the absolute truth about whatever they look upon. We see what happens as they pass from one owner to another.",
        "aired": "December 27, 1960",
        "mediatype": "episode"
      }
    },
    {
      "type": "item",
      "title": "S01E16 - The Hungry Glass",
      "link": "https://archive.org/download/s-01-e-26-papa-benjamin/Thriller%20%281960%29%20-%20COMPLETE/S01E16%20-%20THE%20HUNGRY%20GLASS.ia.mp4",
      "thumbnail": "https://media.themoviedb.org/t/p/w227_and_h127_face/m9qhEBtBWejAzXirSS4SWwy6mwz.jpg",
      "fanart": "https://media.themoviedb.org/t/p/w1920_and_h800_multi_faces/4gFB4BF4zojCrD5JVHp74xWcoQL.jpg",
      "summary": "A young couple buy a run-down, old mansion surrounded with legends about the lack of mirrors and the deaths of many former tenants. On their first night in the house they are frightened by strage visions, inexplicably intertwined with mirrors and glass.",
      "content": "episode",
      "tvshowtitle": "Thriller",
      "season": "1",
      "episode": "16",
      "year": "1961",
      "infolabels": {
        "title": "The Hungry Glass",
        "tvshowtitle": "Thriller",
        "season": 1,
        "episode": 16,
        "plot": "A young couple buy a run-down, old mansion surrounded with legends about the lack of mirrors and the deaths of many former tenants. On their first night in the house they are frightened by strage visions, inexplicably intertwined with mirrors and glass.",
        "aired": "January 3, 1961",
        "mediatype": "episode"
      }
    },
    {
      "type": "item",
      "title": "S01E17 - The Poisoner",
      "link": "https://archive.org/download/s-01-e-26-papa-benjamin/Thriller%20%281960%29%20-%20COMPLETE/S01E17%20-%20THE%20POISONER.ia.mp4",
      "thumbnail": "https://media.themoviedb.org/t/p/w227_and_h127_face/pKK3D0o82QZf3uDtSVTPoCWwE1K.jpg",
      "fanart": "https://media.themoviedb.org/t/p/w1920_and_h800_multi_faces/4gFB4BF4zojCrD5JVHp74xWcoQL.jpg",
      "summary": "A man in nineteenth century England disposes of his family members one by one - his weapon of choice? - an undetectable poison concealed within his ring.",
      "content": "episode",
      "tvshowtitle": "Thriller",
      "season": "1",
      "episode": "17",
      "year": "1961",
      "infolabels": {
        "title": "The Poisoner",
        "tvshowtitle": "Thriller",
        "season": 1,
        "episode": 17,
        "plot": "A man in nineteenth century England disposes of his family members one by one - his weapon of choice? - an undetectable poison concealed within his ring.",
        "aired": "January 10, 1961",
        "mediatype": "episode"
      }
    },
    {
      "type": "item",
      "title": "S01E18 - Man in a Cage",
      "link": "https://archive.org/download/s-01-e-26-papa-benjamin/Thriller%20%281960%29%20-%20COMPLETE/S01E18%20-%20MAN%20IN%20THE%20CAGE.ia.mp4",
      "thumbnail": "https://media.themoviedb.org/t/p/w227_and_h127_face/wWIwEbsDiQWX3X8KVSt4cHZClkl.jpg",
      "fanart": "https://media.themoviedb.org/t/p/w1920_and_h800_multi_faces/4gFB4BF4zojCrD5JVHp74xWcoQL.jpg",
      "summary": "A man arrives in Tangier looking for his missing brother who seems to have been involved in some shady dealings.",
      "content": "episode",
      "tvshowtitle": "Thriller",
      "season": "1",
      "episode": "18",
      "year": "1961",
      "infolabels": {
        "title": "Man in a Cage",
        "tvshowtitle": "Thriller",
        "season": 1,
        "episode": 18,
        "plot": "A man arrives in Tangier looking for his missing brother who seems to have been involved in some shady dealings.",
        "aired": "January 17, 1961",
        "mediatype": "episode"
      }
    },
    {
      "type": "item",
      "title": "S01E19 - Choose a Victim",
      "link": "https://archive.org/download/s-01-e-26-papa-benjamin/Thriller%20%281960%29%20-%20COMPLETE/S01E19%20-%20CHOOSE%20A%20VICTIM.ia.mp4",
      "thumbnail": "https://media.themoviedb.org/t/p/w227_and_h127_face/eomunnvbOpPnk3r64wyNbGu5IXf.jpg",
      "fanart": "https://media.themoviedb.org/t/p/w1920_and_h800_multi_faces/4gFB4BF4zojCrD5JVHp74xWcoQL.jpg",
      "summary": "A wealthy girl takes up with a mercenary beachbum. Together they plot to kill her uncle for his money",
      "content": "episode",
      "tvshowtitle": "Thriller",
      "season": "1",
      "episode": "19",
      "year": "1961",
      "infolabels": {
        "title": "Choose a Victim",
        "tvshowtitle": "Thriller",
        "season": 1,
        "episode": 19,
        "plot": "A wealthy girl takes up with a mercenary beachbum. Together they plot to kill her uncle for his money",
        "aired": "January 24, 1961",
        "mediatype": "episode"
      }
    },
    {
      "type": "item",
      "title": "S01E20 - Hay-Fork and Bill-Hook",
      "link": "https://archive.org/download/s-01-e-26-papa-benjamin/Thriller%20%281960%29%20-%20COMPLETE/S01E20%20-%20HAY-FORK%20AND%20BILL-HOOK.ia.mp4",
      "thumbnail": "https://media.themoviedb.org/t/p/w227_and_h127_face/5Y5EHRcNVCLhwW74Pt3Ls6mnMoL.jpg",
      "fanart": "https://media.themoviedb.org/t/p/w1920_and_h800_multi_faces/4gFB4BF4zojCrD5JVHp74xWcoQL.jpg",
      "summary": "A young detective is sent to the English countryside to investigate a strange murder. His wife, who has accompanied him, soon finds herself a target of the locals who believe she is a witch.",
      "content": "episode",
      "tvshowtitle": "Thriller",
      "season": "1",
      "episode": "20",
      "year": "1961",
      "infolabels": {
        "title": "Hay-Fork and Bill-Hook",
        "tvshowtitle": "Thriller",
        "season": 1,
        "episode": 20,
        "plot": "A young detective is sent to the English countryside to investigate a strange murder. His wife, who has accompanied him, soon finds herself a target of the locals who believe she is a witch.",
        "aired": "February 7, 1961",
        "mediatype": "episode"
      }
    },
    {
      "type": "item",
      "title": "S01E21 - The Merriweather File",
      "link": "https://archive.org/download/s-01-e-26-papa-benjamin/Thriller%20%281960%29%20-%20COMPLETE/S01E21%20-%20The%20Merriweather%20File.ia.mp4",
      "thumbnail": "https://media.themoviedb.org/t/p/w227_and_h127_face/viFxi15JhP5EC7VrlAU47TR3AiR.jpg",
      "fanart": "https://media.themoviedb.org/t/p/w1920_and_h800_multi_faces/4gFB4BF4zojCrD5JVHp74xWcoQL.jpg",
      "summary": "When a man discovers a body in the trunk of his car the harder he tries to prove his innocence the more guilty he looks. Do the attempts on his wife's life have anything to do with this strange case?",
      "content": "episode",
      "tvshowtitle": "Thriller",
      "season": "1",
      "episode": "21",
      "year": "1961",
      "infolabels": {
        "title": "The Merriweather File",
        "tvshowtitle": "Thriller",
        "season": 1,
        "episode": 21,
        "plot": "When a man discovers a body in the trunk of his car the harder he tries to prove his innocence the more guilty he looks. Do the attempts on his wife's life have anything to do with this strange case?",
        "aired": "February 14, 1961",
        "mediatype": "episode"
      }
    },
    {
      "type": "item",
      "title": "S01E22 - The Fingers of Fear",
      "link": "https://archive.org/download/s-01-e-26-papa-benjamin/Thriller%20%281960%29%20-%20COMPLETE/S01E22%20-%20The%20Fingers%20of%20Fear.ia.mp4",
      "thumbnail": "https://media.themoviedb.org/t/p/w227_and_h127_face/ak5jLfBQOLzAqP0ioJNmdF34DOA.jpg",
      "fanart": "https://media.themoviedb.org/t/p/w1920_and_h800_multi_faces/4gFB4BF4zojCrD5JVHp74xWcoQL.jpg",
      "summary": "A child murderer is on the loose. A mentally disturbed man is arrested for the crimes, but a determined police lieutenant isn't sure they have the right man.",
      "content": "episode",
      "tvshowtitle": "Thriller",
      "season": "1",
      "episode": "22",
      "year": "1961",
      "infolabels": {
        "title": "The Fingers of Fear",
        "tvshowtitle": "Thriller",
        "season": 1,
        "episode": 22,
        "plot": "A child murderer is on the loose. A mentally disturbed man is arrested for the crimes, but a determined police lieutenant isn't sure they have the right man.",
        "aired": "February 21, 1961",
        "mediatype": "episode"
      }
    },
    {
      "type": "item",
      "title": "S01E23 - Well of Doom",
      "link": "https://archive.org/download/s-01-e-26-papa-benjamin/Thriller%20%281960%29%20-%20COMPLETE/S01E23%20-%20Well%20Of%20Doom.ia.mp4",
      "thumbnail": "https://media.themoviedb.org/t/p/w500/lLrNBo5Krzu1oNlxEqKprk8UW5b.jpg",
      "fanart": "https://media.themoviedb.org/t/p/w1920_and_h800_multi_faces/4gFB4BF4zojCrD5JVHp74xWcoQL.jpg",
      "summary": "A man is kidnapped on the eve of his wedding and held prisoner by a ghoulish creature claiming to be the devil himself.",
      "content": "episode",
      "tvshowtitle": "Thriller",
      "season": "1",
      "episode": "23",
      "year": "1961",
      "infolabels": {
        "title": "Well of Doom",
        "tvshowtitle": "Thriller",
        "season": 1,
        "episode": 23,
        "plot": "A man is kidnapped on the eve of his wedding and held prisoner by a ghoulish creature claiming to be the devil himself.",
        "aired": "February 28, 1961",
        "mediatype": "episode"
      }
    },
    {
      "type": "item",
      "title": "S01E24 - The Ordeal of Dr. Cordell",
      "link": "https://archive.org/download/s-01-e-26-papa-benjamin/Thriller%20%281960%29%20-%20COMPLETE/S01E24%20-%20The%20Ordeal%20of%20Dr.%20Cordell.ia.mp4",
      "thumbnail": "https://media.themoviedb.org/t/p/w227_and_h127_face/faDmzEmmLg2B8aLZa4mEEac7EqD.jpg",
      "fanart": "https://media.themoviedb.org/t/p/w1920_and_h800_multi_faces/4gFB4BF4zojCrD5JVHp74xWcoQL.jpg",
      "summary": "A research scientist accidentally discovers a strange gas that penetrates his gas mask and the effects are most bizarre - now every time he hears a bell it sends him into a murderous rage.",
      "content": "episode",
      "tvshowtitle": "Thriller",
      "season": "1",
      "episode": "24",
      "year": "1961",
      "infolabels": {
        "title": "The Ordeal of Dr. Cordell",
        "tvshowtitle": "Thriller",
        "season": 1,
        "episode": 24,
        "plot": "A research scientist accidentally discovers a strange gas that penetrates his gas mask and the effects are most bizarre - now every time he hears a bell it sends him into a murderous rage.",
        "aired": "March 7, 1961",
        "mediatype": "episode"
      }
    },
    {
      "type": "item",
      "title": "S01E25 - Trio for Terror",
      "link": "https://archive.org/download/s-01-e-26-papa-benjamin/Thriller%20%281960%29%20-%20COMPLETE/S01E25%20-%20Trio%20for%20Terror.ia.mp4",
      "thumbnail": "https://media.themoviedb.org/t/p/w227_and_h127_face/dr447ZAw51NEcFbJ2dDnlgbssbG.jpg",
      "fanart": "https://media.themoviedb.org/t/p/w1920_and_h800_multi_faces/4gFB4BF4zojCrD5JVHp74xWcoQL.jpg",
      "summary": "Three separate tales: a man murders his uncle for the inheritance, but the uncle is no oridinary man; a man wins a fortune gambling, but may not live to enjoy it; a serial killer meets an odd fate.",
      "content": "episode",
      "tvshowtitle": "Thriller",
      "season": "1",
      "episode": "25",
      "year": "1961",
      "infolabels": {
        "title": "Trio for Terror",
        "tvshowtitle": "Thriller",
        "season": 1,
        "episode": 25,
        "plot": "Three separate tales: a man murders his uncle for the inheritance, but the uncle is no oridinary man; a man wins a fortune gambling, but may not live to enjoy it; a serial killer meets an odd fate.",
        "aired": "March 14, 1961",
        "mediatype": "episode"
      }
    },
    {
      "type": "item",
      "title": "S01E26 - Papa Benjamin",
      "link": "https://archive.org/download/s-01-e-26-papa-benjamin/Thriller%20%281960%29%20-%20COMPLETE/S01E26%20-%20Papa%20Benjamin.ia.mp4",
      "thumbnail": "https://media.themoviedb.org/t/p/w227_and_h127_face/zdXlDwi2GThANCizvamlQZnQrDe.jpg",
      "fanart": "https://media.themoviedb.org/t/p/w1920_and_h800_multi_faces/4gFB4BF4zojCrD5JVHp74xWcoQL.jpg",
      "summary": "A musician tells a strange tale of involvement in a voodoo cult.",
      "content": "episode",
      "tvshowtitle": "Thriller",
      "season": "1",
      "episode": "26",
      "year": "1961",
      "infolabels": {
        "title": "Papa Benjamin",
        "tvshowtitle": "Thriller",
        "season": 1,
        "episode": 26,
        "plot": "A musician tells a strange tale of involvement in a voodoo cult.",
        "aired": "March 21, 1961",
        "mediatype": "episode"
      }
    },
    {
      "type": "item",
      "title": "S01E27 - Late Date",
      "link": "https://archive.org/download/s-01-e-26-papa-benjamin/Thriller%20%281960%29%20-%20COMPLETE/S01E27%20-%20Late%20Date.ia.mp4",
      "thumbnail": "https://media.themoviedb.org/t/p/w227_and_h127_face/vYEQhkYXswg6mLNuuPMqbXA7Plt.jpg",
      "fanart": "https://media.themoviedb.org/t/p/w1920_and_h800_multi_faces/4gFB4BF4zojCrD5JVHp74xWcoQL.jpg",
      "summary": "When a man murders his adulterous wife his brother attempts to conceal the crime by disposing of the body - but it won't be easy.",
      "content": "episode",
      "tvshowtitle": "Thriller",
      "season": "1",
      "episode": "27",
      "year": "1961",
      "infolabels": {
        "title": "Late Date",
        "tvshowtitle": "Thriller",
        "season": 1,
        "episode": 27,
        "plot": "When a man murders his adulterous wife his brother attempts to conceal the crime by disposing of the body - but it won't be easy.",
        "aired": "April 4, 1961",
        "mediatype": "episode"
      }
    },
    {
      "type": "item",
      "title": "S01E28 - Yours Truly, Jack the Ripper",
      "link": "https://archive.org/download/s-01-e-26-papa-benjamin/Thriller%20%281960%29%20-%20COMPLETE/S01E28%20-%20Yours%20Truly%2C%20Jack%20the%20Ripper.mp4",
      "thumbnail": "https://media.themoviedb.org/t/p/w227_and_h127_face/m2CESfYGN0rZkGINetl2zP5w5D6.jpg",
      "fanart": "https://media.themoviedb.org/t/p/w1920_and_h800_multi_faces/4gFB4BF4zojCrD5JVHp74xWcoQL.jpg",
      "summary": "A series of brutal murders in the modern-day U.S. mirror those of Jack the Ripper. Sir Guy informs the police of his theory that it is in fact the Ripper himself, alive and well - and not a year older.",
      "content": "episode",
      "tvshowtitle": "Thriller",
      "season": "1",
      "episode": "28",
      "year": "1961",
      "infolabels": {
        "title": "Yours Truly, Jack the Ripper",
        "tvshowtitle": "Thriller",
        "season": 1,
        "episode": 28,
        "plot": "A series of brutal murders in the modern-day U.S. mirror those of Jack the Ripper. Sir Guy informs the police of his theory that it is in fact the Ripper himself, alive and well - and not a year older.",
        "aired": "April 11, 1961",
        "mediatype": "episode"
      }
    },
    {
      "type": "item",
      "title": "S01E29 - The Devil's Ticket",
      "link": "https://archive.org/download/s-01-e-26-papa-benjamin/Thriller%20%281960%29%20-%20COMPLETE/S01E29%20-%20The%20Devil%27s%20Ticket.ia.mp4",
      "thumbnail": "https://media.themoviedb.org/t/p/w227_and_h127_face/dePEJ5J3RS2MFAcWGnRYfVCNKfh.jpg",
      "fanart": "https://media.themoviedb.org/t/p/w1920_and_h800_multi_faces/4gFB4BF4zojCrD5JVHp74xWcoQL.jpg",
      "summary": "A starving artist goes to a pawn shop with one of his paintings and ends up pawning his soul to the devil. Will he be able to redeem it when the time comes?",
      "content": "episode",
      "tvshowtitle": "Thriller",
      "season": "1",
      "episode": "29",
      "year": "1961",
      "infolabels": {
        "title": "The Devil's Ticket",
        "tvshowtitle": "Thriller",
        "season": 1,
        "episode": 29,
        "plot": "A starving artist goes to a pawn shop with one of his paintings and ends up pawning his soul to the devil. Will he be able to redeem it when the time comes?",
        "aired": "April 18, 1961",
        "mediatype": "episode"
      }
    },
    {
      "type": "item",
      "title": "S01E30 - Parasite Mansion",
      "link": "https://archive.org/download/s-01-e-26-papa-benjamin/Thriller%20%281960%29%20-%20COMPLETE/S01E30%20-%20Parasite%20Mansion.ia.mp4",
      "thumbnail": "https://media.themoviedb.org/t/p/w227_and_h127_face/wB7QHhRdOnrc6oV40EskkaYP0Si.jpg",
      "fanart": "https://media.themoviedb.org/t/p/w1920_and_h800_multi_faces/4gFB4BF4zojCrD5JVHp74xWcoQL.jpg",
      "summary": "A young teacher is lost during a storm and wakes up to find herself held prisoner in a run-down mansion inhabited by a strange and terrifying family.",
      "content": "episode",
      "tvshowtitle": "Thriller",
      "season": "1",
      "episode": "30",
      "year": "1961",
      "infolabels": {
        "title": "Parasite Mansion",
        "tvshowtitle": "Thriller",
        "season": 1,
        "episode": 30,
        "plot": "A young teacher is lost during a storm and wakes up to find herself held prisoner in a run-down mansion inhabited by a strange and terrifying family.",
        "aired": "April 25, 1961",
        "mediatype": "episode"
      }
    },
    {
      "type": "item",
      "title": "S01E31 - A Good Imagination",
      "link": "https://archive.org/download/s-01-e-26-papa-benjamin/Thriller%20%281960%29%20-%20COMPLETE/S01E31%20-%20A%20GOOD%20IMAGINATION.ia.mp4",
      "thumbnail": "https://media.themoviedb.org/t/p/w227_and_h127_face/s0y2vGJNprCH9f6OymawC1AaOBd.jpg",
      "fanart": "https://media.themoviedb.org/t/p/w1920_and_h800_multi_faces/4gFB4BF4zojCrD5JVHp74xWcoQL.jpg",
      "summary": "A book dealer turns to murder over his adulterous wife - taking his methods for killing from classic literature.",
      "content": "episode",
      "tvshowtitle": "Thriller",
      "season": "1",
      "episode": "31",
      "year": "1961",
      "infolabels": {
        "title": "A Good Imagination",
        "tvshowtitle": "Thriller",
        "season": 1,
        "episode": 31,
        "plot": "A book dealer turns to murder over his adulterous wife - taking his methods for killing from classic literature.",
        "aired": "May 2, 1961",
        "mediatype": "episode"
      }
    },
    {
      "type": "item",
      "title": "S01E32 - Mr. George",
      "link": "https://archive.org/download/s-01-e-26-papa-benjamin/Thriller%20%281960%29%20-%20COMPLETE/S01E32%20-%20MR%20%20GEORGE.ia.mp4",
      "thumbnail": "https://media.themoviedb.org/t/p/w227_and_h127_face/za3EldoW1zr9aTXuAd7ElhJ3S6o.jpg",
      "fanart": "https://media.themoviedb.org/t/p/w1920_and_h800_multi_faces/4gFB4BF4zojCrD5JVHp74xWcoQL.jpg",
      "summary": "A little girl is the sole heir to her mother's fortune and her greedy relatives are out to kill her for her money. What they don't realize is this little girl has a supernatural guardian.",
      "content": "episode",
      "tvshowtitle": "Thriller",
      "season": "1",
      "episode": "32",
      "year": "1961",
      "infolabels": {
        "title": "Mr. George",
        "tvshowtitle": "Thriller",
        "season": 1,
        "episode": 32,
        "plot": "A little girl is the sole heir to her mother's fortune and her greedy relatives are out to kill her for her money. What they don't realize is this little girl has a supernatural guardian.",
        "aired": "May 9, 1961",
        "mediatype": "episode"
      }
    },
    {
      "type": "item",
      "title": "S01E33 - Terror in Teakwood",
      "link": "https://archive.org/download/s-01-e-26-papa-benjamin/Thriller%20%281960%29%20-%20COMPLETE/S01E33%20-%20The%20Terror%20in%20Teakwood.ia.mp4",
      "thumbnail": "https://media.themoviedb.org/t/p/w227_and_h127_face/xljNvGU6PfnfxXxualn6YgZ2vBy.jpg",
      "fanart": "https://media.themoviedb.org/t/p/w1920_and_h800_multi_faces/4gFB4BF4zojCrD5JVHp74xWcoQL.jpg",
      "summary": "A young man's former girlfriend comes to him for help; her husband, a famous pianist, is being terrorized by an unknown being - is it a dead rival, secretly alive, or is it something much more grotesque.",
      "content": "episode",
      "tvshowtitle": "Thriller",
      "season": "1",
      "episode": "33",
      "year": "1961",
      "infolabels": {
        "title": "Terror in Teakwood",
        "tvshowtitle": "Thriller",
        "season": 1,
        "episode": 33,
        "plot": "A young man's former girlfriend comes to him for help; her husband, a famous pianist, is being terrorized by an unknown being - is it a dead rival, secretly alive, or is it something much more grotesque.",
        "aired": "May 16, 1961",
        "mediatype": "episode"
      }
    },
    {
      "type": "item",
      "title": "S01E34 - The Prisoner in the Mirror",
      "link": "https://archive.org/download/s-01-e-26-papa-benjamin/Thriller%20%281960%29%20-%20COMPLETE/S01E34%20%20-%20THE%20PRISONER%20IN%20THE%20MIRROR.ia.mp4",
      "thumbnail": "https://media.themoviedb.org/t/p/w227_and_h127_face/zo2VgYCPp7HPqhB97PqoNPoGIKy.jpg",
      "fanart": "https://media.themoviedb.org/t/p/w1920_and_h800_multi_faces/4gFB4BF4zojCrD5JVHp74xWcoQL.jpg",
      "summary": "A professor researching an eighteenth century murderous magician purchases a mirror in Paris only to find the magician's victims imprisoned within - or is it only a trick?",
      "content": "episode",
      "tvshowtitle": "Thriller",
      "season": "1",
      "episode": "34",
      "year": "1961",
      "infolabels": {
        "title": "The Prisoner in the Mirror",
        "tvshowtitle": "Thriller",
        "season": 1,
        "episode": 34,
        "plot": "A professor researching an eighteenth century murderous magician purchases a mirror in Paris only to find the magician's victims imprisoned within - or is it only a trick?",
        "aired": "May 23, 1961",
        "mediatype": "episode"
      }
    },
    {
      "type": "item",
      "title": "S01E35 - Dark Legacy",
      "link": "https://archive.org/download/s-01-e-26-papa-benjamin/Thriller%20%281960%29%20-%20COMPLETE/S01E35%20-%20Dark%20Legacy.ia.mp4",
      "thumbnail": "https://media.themoviedb.org/t/p/w227_and_h127_face/yubad3oja0HgoSqiNpTNTtlLtZK.jpg",
      "fanart": "https://media.themoviedb.org/t/p/w1920_and_h800_multi_faces/4gFB4BF4zojCrD5JVHp74xWcoQL.jpg",
      "summary": "The patriarch of a family of magicians dies and leaves his nephew his book of secrets - and it is indeed a dark legacy involving satanic spirits and black magic.",
      "content": "episode",
      "tvshowtitle": "Thriller",
      "season": "1",
      "episode": "35",
      "year": "1961",
      "infolabels": {
        "title": "Dark Legacy",
        "tvshowtitle": "Thriller",
        "season": 1,
        "episode": 35,
        "plot": "The patriarch of a family of magicians dies and leaves his nephew his book of secrets - and it is indeed a dark legacy involving satanic spirits and black magic.",
        "aired": "May 30, 1961",
        "mediatype": "episode"
      }
    },
    {
      "type": "item",
      "title": "S01E36 - Pigeons From Hell",
      "link": "https://archive.org/download/s-01-e-26-papa-benjamin/Thriller%20%281960%29%20-%20COMPLETE/S01E36%20-%20PIGEONS%20FROM%20HELL.ia.mp4",
      "thumbnail": "https://media.themoviedb.org/t/p/w227_and_h127_face/qedL2mmm4vS5W0uUsRotqf6ysfj.jpg",
      "fanart": "https://media.themoviedb.org/t/p/w1920_and_h800_multi_faces/4gFB4BF4zojCrD5JVHp74xWcoQL.jpg",
      "summary": "Two young brothers attempt to spend the night in an abandoned southern plantation and encounter some birds that seem to have a strong dislike for intruders.",
      "content": "episode",
      "tvshowtitle": "Thriller",
      "season": "1",
      "episode": "36",
      "year": "1961",
      "infolabels": {
        "title": "Pigeons From Hell",
        "tvshowtitle": "Thriller",
        "season": 1,
        "episode": 36,
        "plot": "Two young brothers attempt to spend the night in an abandoned southern plantation and encounter some birds that seem to have a strong dislike for intruders.",
        "aired": "June 6, 1961",
        "mediatype": "episode"
      }
    },
    {
      "type": "item",
      "title": "S01E37 - The Grim Reaper",
      "link": "https://archive.org/download/s-01-e-26-papa-benjamin/Thriller%20%281960%29%20-%20COMPLETE/S01E37%20-%20THE%20GRIM%20REAPER.ia.mp4",
      "thumbnail": "https://media.themoviedb.org/t/p/w227_and_h127_face/tLRCWMtyr7VMfo6khC256fXCwxU.jpg",
      "fanart": "https://media.themoviedb.org/t/p/w1920_and_h800_multi_faces/4gFB4BF4zojCrD5JVHp74xWcoQL.jpg",
      "summary": "An eccentric mystery writer purchases a ghoulish painting of the grim reaper which happens to have a curse on it - almost all of its former owners have died. When the owner's life is in danger the painting sends a gruesome warning - it begins to bleed.",
      "content": "episode",
      "tvshowtitle": "Thriller",
      "season": "1",
      "episode": "37",
      "year": "1961",
      "infolabels": {
        "title": "The Grim Reaper",
        "tvshowtitle": "Thriller",
        "season": 1,
        "episode": 37,
        "plot": "An eccentric mystery writer purchases a ghoulish painting of the grim reaper which happens to have a curse on it - almost all of its former owners have died. When the owner's life is in danger the painting sends a gruesome warning - it begins to bleed.",
        "aired": "June 13, 1961",
        "mediatype": "episode"
      }
    },
    {
      "type": "item",
      "title": "S02E01 - What Beckoning Ghost?",
      "link": "https://archive.org/download/s-01-e-26-papa-benjamin/Thriller%20%281960%29%20-%20COMPLETE/S02E01%20-%20WHAT%20BECKONING%20GHOST%EF%BC%9F.ia.mp4",
      "thumbnail": "https://media.themoviedb.org/t/p/w227_and_h127_face/6vWhQxjXZBB8x5RTMJQbiKbn36Y.jpg",
      "fanart": "https://media.themoviedb.org/t/p/w1920_and_h800_multi_faces/4gFB4BF4zojCrD5JVHp74xWcoQL.jpg",
      "summary": "An ailing pianist fears she is losing her mind when she begins seeing what she thinks is her own funeral.",
      "content": "episode",
      "tvshowtitle": "Thriller",
      "season": "2",
      "episode": "1",
      "year": "1961",
      "infolabels": {
        "title": "What Beckoning Ghost?",
        "tvshowtitle": "Thriller",
        "season": 2,
        "episode": 1,
        "plot": "An ailing pianist fears she is losing her mind when she begins seeing what she thinks is her own funeral.",
        "aired": "September 18, 1961",
        "mediatype": "episode"
      }
    },
    {
      "type": "item",
      "title": "S02E02 - Guillotine",
      "link": "https://archive.org/download/s-01-e-26-papa-benjamin/Thriller%20%281960%29%20-%20COMPLETE/S02E02%20-%20Guillotine.ia.mp4",
      "thumbnail": "https://media.themoviedb.org/t/p/w227_and_h127_face/ovLS33ys6shC4TOCMDUsKpwBsgy.jpg",
      "fanart": "https://media.themoviedb.org/t/p/w1920_and_h800_multi_faces/4gFB4BF4zojCrD5JVHp74xWcoQL.jpg",
      "summary": "To save the life of her husband who is to be executed, a young woman attempts to murder the executioner.",
      "content": "episode",
      "tvshowtitle": "Thriller",
      "season": "2",
      "episode": "2",
      "year": "1961",
      "infolabels": {
        "title": "Guillotine",
        "tvshowtitle": "Thriller",
        "season": 2,
        "episode": 2,
        "plot": "To save the life of her husband who is to be executed, a young woman attempts to murder the executioner.",
        "aired": "September 26, 1961",
        "mediatype": "episode"
      }
    },
    {
      "type": "item",
      "title": "S02E03 - The Premature Burial",
      "link": "https://archive.org/download/s-01-e-26-papa-benjamin/Thriller%20%281960%29%20-%20COMPLETE/S02E03%20-%20THE%20PREMATURE%20BURIAL.ia.mp4",
      "thumbnail": "https://media.themoviedb.org/t/p/w227_and_h127_face/vqqhkUd2UFCMltUqzQqpyoEK7oq.jpg",
      "fanart": "https://media.themoviedb.org/t/p/w1920_and_h800_multi_faces/4gFB4BF4zojCrD5JVHp74xWcoQL.jpg",
      "summary": "When a man is accidentally buried alive and then saved he becomes paranoid that it might happen again - and he has good reason to be scared - his new wife is anxious to become a widow.",
      "content": "episode",
      "tvshowtitle": "Thriller",
      "season": "2",
      "episode": "3",
      "year": "1961",
      "infolabels": {
        "title": "The Premature Burial",
        "tvshowtitle": "Thriller",
        "season": 2,
        "episode": 3,
        "plot": "When a man is accidentally buried alive and then saved he becomes paranoid that it might happen again - and he has good reason to be scared - his new wife is anxious to become a widow.",
        "aired": "October 2, 1961",
        "mediatype": "episode"
      }
    },
    {
      "type": "item",
      "title": "S02E04 - The Weird Tailor",
      "link": "https://archive.org/download/s-01-e-26-papa-benjamin/Thriller%20%281960%29%20-%20COMPLETE/S02E04%20-%20THE%20WEIRD%20TAILOR.ia.mp4",
      "thumbnail": "https://media.themoviedb.org/t/p/w227_and_h127_face/m7Mwjp40I9SwAWdx9xsnzCwNZde.jpg",
      "fanart": "https://media.themoviedb.org/t/p/w1920_and_h800_multi_faces/4gFB4BF4zojCrD5JVHp74xWcoQL.jpg",
      "summary": "A man attempts to bring his dead son back to life with the use of black magic and an unusual suit of clothes.",
      "content": "episode",
      "tvshowtitle": "Thriller",
      "season": "2",
      "episode": "4",
      "year": "1961",
      "infolabels": {
        "title": "The Weird Tailor",
        "tvshowtitle": "Thriller",
        "season": 2,
        "episode": 4,
        "plot": "A man attempts to bring his dead son back to life with the use of black magic and an unusual suit of clothes.",
        "aired": "October 16, 1961",
        "mediatype": "episode"
      }
    },
    {
      "type": "item",
      "title": "S02E05 - God Grante That She Lye Stille",
      "link": "https://archive.org/download/s-01-e-26-papa-benjamin/Thriller%20%281960%29%20-%20COMPLETE/S02E05%20-%20God%20Grante%20that%20She%20Lye%20Stille.ia.mp4",
      "thumbnail": "https://media.themoviedb.org/t/p/w227_and_h127_face/bV47DSGn9PUOqp5IoQ8Us1MOEZ2.jpg",
      "fanart": "https://media.themoviedb.org/t/p/w1920_and_h800_multi_faces/4gFB4BF4zojCrD5JVHp74xWcoQL.jpg",
      "summary": "A 300-year-old witch seeks to possess the last of her family line, beautiful young Lady Margaret.",
      "content": "episode",
      "tvshowtitle": "Thriller",
      "season": "2",
      "episode": "5",
      "year": "1961",
      "infolabels": {
        "title": "God Grante That She Lye Stille",
        "tvshowtitle": "Thriller",
        "season": 2,
        "episode": 5,
        "plot": "A 300-year-old witch seeks to possess the last of her family line, beautiful young Lady Margaret.",
        "aired": "October 23, 1961",
        "mediatype": "episode"
      }
    },
    {
      "type": "item",
      "title": "S02E06 - Masquerade",
      "link": "https://archive.org/download/s-01-e-26-papa-benjamin/Thriller%20%281960%29%20-%20COMPLETE/S02E06%20-%20MASQUERADE.ia.mp4",
      "thumbnail": "https://media.themoviedb.org/t/p/w227_and_h127_face/5aAtmQeYZsDOGWBjZ04VttDmJO7.jpg",
      "fanart": "https://media.themoviedb.org/t/p/w1920_and_h800_multi_faces/4gFB4BF4zojCrD5JVHp74xWcoQL.jpg",
      "summary": "A young couple take refuge in a spooky house on a stormy night and are terrorized by the strange family who occupy it. But do the young honeymooners have a secret of their own?",
      "content": "episode",
      "tvshowtitle": "Thriller",
      "season": "2",
      "episode": "6",
      "year": "1961",
      "infolabels": {
        "title": "Masquerade",
        "tvshowtitle": "Thriller",
        "season": 2,
        "episode": 6,
        "plot": "A young couple take refuge in a spooky house on a stormy night and are terrorized by the strange family who occupy it. But do the young honeymooners have a secret of their own?",
        "aired": "October 30, 1961",
        "mediatype": "episode"
      }
    },
    {
      "type": "item",
      "title": "S02E07 - The Last of the Sommervilles",
      "link": "https://archive.org/download/s-01-e-26-papa-benjamin/Thriller%20%281960%29%20-%20COMPLETE/S02E07%20%20-%20THE%20LAST%20OF%20THE%20SOMMERVILLES.ia.mp4",
      "thumbnail": "https://media.themoviedb.org/t/p/w227_and_h127_face/hk19EsGkB4spI3y4AeOjejIyKXS.jpg",
      "fanart": "https://media.themoviedb.org/t/p/w1920_and_h800_multi_faces/4gFB4BF4zojCrD5JVHp74xWcoQL.jpg",
      "summary": "Two cousins scheme to kill their aunt for her money - but trust is hard to come by when you're the last of the Sommervilles.",
      "content": "episode",
      "tvshowtitle": "Thriller",
      "season": "2",
      "episode": "7",
      "year": "1961",
      "infolabels": {
        "title": "The Last of the Sommervilles",
        "tvshowtitle": "Thriller",
        "season": 2,
        "episode": 7,
        "plot": "Two cousins scheme to kill their aunt for her money - but trust is hard to come by when you're the last of the Sommervilles.",
        "aired": "November 6, 1961",
        "mediatype": "episode"
      }
    },
    {
      "type": "item",
      "title": "S02E08 - Letter to a Lover",
      "link": "https://archive.org/download/s-01-e-26-papa-benjamin/Thriller%20%281960%29%20-%20COMPLETE/S02E08%20-%20Letter%20to%20a%20Lover.ia.mp4",
      "thumbnail": "https://media.themoviedb.org/t/p/w227_and_h127_face/cPRV9NStSKrODbVhrv3iqmzL2Py.jpg",
      "fanart": "https://media.themoviedb.org/t/p/w1920_and_h800_multi_faces/4gFB4BF4zojCrD5JVHp74xWcoQL.jpg",
      "summary": "When a doctor is murdered two of the chief suspects, a husband and wife, seem to be accusing each other of insanity - which one of them is correct?",
      "content": "episode",
      "tvshowtitle": "Thriller",
      "season": "2",
      "episode": "8",
      "year": "1961",
      "infolabels": {
        "title": "Letter to a Lover",
        "tvshowtitle": "Thriller",
        "season": 2,
        "episode": 8,
        "plot": "When a doctor is murdered two of the chief suspects, a husband and wife, seem to be accusing each other of insanity - which one of them is correct?",
        "aired": "November 13, 1961",
        "mediatype": "episode"
      }
    },
    {
      "type": "item",
      "title": "S02E09 - A Third For Pinochle",
      "link": "https://archive.org/download/s-01-e-26-papa-benjamin/Thriller%20%281960%29%20-%20COMPLETE/S02E09%20-%20A%20THIRD%20FOR%20PINOCHLE.ia.mp4",
      "thumbnail": "https://media.themoviedb.org/t/p/w227_and_h127_face/iUoEj32pJIAHE8RZ1o8ndoa6x8S.jpg",
      "fanart": "https://media.themoviedb.org/t/p/w1920_and_h800_multi_faces/4gFB4BF4zojCrD5JVHp74xWcoQL.jpg",
      "summary": "A man plans to murder his wife using his nosy neighbors for an alibi - but the eccentric ladies across the street may have a trick or two up their sleeve.",
      "content": "episode",
      "tvshowtitle": "Thriller",
      "season": "2",
      "episode": "9",
      "year": "1961",
      "infolabels": {
        "title": "A Third For Pinochle",
        "tvshowtitle": "Thriller",
        "season": 2,
        "episode": 9,
        "plot": "A man plans to murder his wife using his nosy neighbors for an alibi - but the eccentric ladies across the street may have a trick or two up their sleeve.",
        "aired": "November 20, 1961",
        "mediatype": "episode"
      }
    },
    {
      "type": "item",
      "title": "S02E10 - The Closed Cabinet",
      "link": "https://archive.org/download/s-01-e-26-papa-benjamin/Thriller%20%281960%29%20-%20COMPLETE/S02E10%20-%20The%20Closed%20Cabinet.ia.mp4",
      "thumbnail": "https://media.themoviedb.org/t/p/w227_and_h127_face/5ZisxU0OZxp8r0AawDJunLHMVOJ.jpg",
      "fanart": "https://media.themoviedb.org/t/p/w1920_and_h800_multi_faces/4gFB4BF4zojCrD5JVHp74xWcoQL.jpg",
      "summary": "A young woman visiting an ancient English castle learns a thing or two about the family curse. Will she be able to remove it by finding a way to open the closed cabinet?",
      "content": "episode",
      "tvshowtitle": "Thriller",
      "season": "2",
      "episode": "10",
      "year": "1961",
      "infolabels": {
        "title": "The Closed Cabinet",
        "tvshowtitle": "Thriller",
        "season": 2,
        "episode": 10,
        "plot": "A young woman visiting an ancient English castle learns a thing or two about the family curse. Will she be able to remove it by finding a way to open the closed cabinet?",
        "aired": "November 27, 1961",
        "mediatype": "episode"
      }
    },
    {
      "type": "item",
      "title": "S02E11 - Dialogues With Death",
      "link": "https://archive.org/download/s-01-e-26-papa-benjamin/Thriller%20%281960%29%20-%20COMPLETE/S02E11%20-%20Dialogues%20with%20Death.ia.mp4",
      "thumbnail": "https://media.themoviedb.org/t/p/w227_and_h127_face/9vJZfvEd5aV0qQmqcUIuS1icgxr.jpg",
      "fanart": "https://media.themoviedb.org/t/p/w1920_and_h800_multi_faces/4gFB4BF4zojCrD5JVHp74xWcoQL.jpg",
      "summary": "Two separate tales: a morgue attendent seems to be able to talk to the corpses, and get an answer; a young couple arrive at the home of their aunt and uncle who seem to believe the pair are dead no matter how much they protest.",
      "content": "episode",
      "tvshowtitle": "Thriller",
      "season": "2",
      "episode": "11",
      "year": "1961",
      "infolabels": {
        "title": "Dialogues With Death",
        "tvshowtitle": "Thriller",
        "season": 2,
        "episode": 11,
        "plot": "Two separate tales: a morgue attendent seems to be able to talk to the corpses, and get an answer; a young couple arrive at the home of their aunt and uncle who seem to believe the pair are dead no matter how much they protest.",
        "aired": "December 4, 1961",
        "mediatype": "episode"
      }
    },
    {
      "type": "item",
      "title": "S02E12 - The Return of Andrew Bentley",
      "link": "https://archive.org/download/s-01-e-26-papa-benjamin/Thriller%20%281960%29%20-%20COMPLETE/S02E12%20-%20The%20Return%20of%20Andrew%20Bentley.ia.mp4",
      "thumbnail": "https://media.themoviedb.org/t/p/w227_and_h127_face/syert0uc8Yq7gszzbxMKUeeJ9RR.jpg",
      "fanart": "https://media.themoviedb.org/t/p/w1920_and_h800_multi_faces/4gFB4BF4zojCrD5JVHp74xWcoQL.jpg",
      "summary": "A man inherits his uncle's estate on the condition that he spend twenty-four hours a day in the house and guard his uncle's grave against a supernatural intruder.",
      "content": "episode",
      "tvshowtitle": "Thriller",
      "season": "2",
      "episode": "12",
      "year": "1961",
      "infolabels": {
        "title": "The Return of Andrew Bentley",
        "tvshowtitle": "Thriller",
        "season": 2,
        "episode": 12,
        "plot": "A man inherits his uncle's estate on the condition that he spend twenty-four hours a day in the house and guard his uncle's grave against a supernatural intruder.",
        "aired": "December 11, 1961",
        "mediatype": "episode"
      }
    },
    {
      "type": "item",
      "title": "S02E13 - The Remarkable Mrs. Hawk",
      "link": "https://archive.org/download/s-01-e-26-papa-benjamin/Thriller%20%281960%29%20-%20COMPLETE/S02E13%20-%20THE%20REMARKABLE%20MRS%20%20HAWK.ia.mp4",
      "thumbnail": "https://media.themoviedb.org/t/p/w227_and_h127_face/qz96uXMirbdvWZJ0OgOi9YGcShi.jpg",
      "fanart": "https://media.themoviedb.org/t/p/w1920_and_h800_multi_faces/4gFB4BF4zojCrD5JVHp74xWcoQL.jpg",
      "summary": "Mrs. Hawk has a talent for raising prize hogs - but the secret of her success is more sinister than anyone could imagine.",
      "content": "episode",
      "tvshowtitle": "Thriller",
      "season": "2",
      "episode": "13",
      "year": "1961",
      "infolabels": {
        "title": "The Remarkable Mrs. Hawk",
        "tvshowtitle": "Thriller",
        "season": 2,
        "episode": 13,
        "plot": "Mrs. Hawk has a talent for raising prize hogs - but the secret of her success is more sinister than anyone could imagine.",
        "aired": "December 18, 1961",
        "mediatype": "episode"
      }
    },
    {
      "type": "item",
      "title": "S02E14 - Portrait Without a Face",
      "link": "https://archive.org/download/s-01-e-26-papa-benjamin/Thriller%20%281960%29%20-%20COMPLETE/S02E14%20-%20Portrait%20Without%20a%20Face.ia.mp4",
      "thumbnail": "https://media.themoviedb.org/t/p/w227_and_h127_face/2ccSF3EovhecBiH92hA7lMPpu5v.jpg",
      "fanart": "https://media.themoviedb.org/t/p/w1920_and_h800_multi_faces/4gFB4BF4zojCrD5JVHp74xWcoQL.jpg",
      "summary": "After a dispicable artist is murdered his last painting seems to be completing itself and revealing the artist's killer - or is it?",
      "content": "episode",
      "tvshowtitle": "Thriller",
      "season": "2",
      "episode": "14",
      "year": "1961",
      "infolabels": {
        "title": "Portrait Without a Face",
        "tvshowtitle": "Thriller",
        "season": 2,
        "episode": 14,
        "plot": "After a dispicable artist is murdered his last painting seems to be completing itself and revealing the artist's killer - or is it?",
        "aired": "December 25, 1961",
        "mediatype": "episode"
      }
    },
    {
      "type": "item",
      "title": "S02E15 - An Attractive Family",
      "link": "https://archive.org/download/s-01-e-26-papa-benjamin/Thriller%20%281960%29%20-%20COMPLETE/S02E15%20-%20AN%20ATTRACTIVE%20FAMILY.ia.mp4",
      "thumbnail": "https://media.themoviedb.org/t/p/w227_and_h127_face/k90HpanOyahLJAUFyKFfgwpNWON.jpg",
      "fanart": "https://media.themoviedb.org/t/p/w1920_and_h800_multi_faces/4gFB4BF4zojCrD5JVHp74xWcoQL.jpg",
      "summary": "An attractive family of serial murderers plan the death of another victim - their young sister-in-law.",
      "content": "episode",
      "tvshowtitle": "Thriller",
      "season": "2",
      "episode": "15",
      "year": "1962",
      "infolabels": {
        "title": "An Attractive Family",
        "tvshowtitle": "Thriller",
        "season": 2,
        "episode": 15,
        "plot": "An attractive family of serial murderers plan the death of another victim - their young sister-in-law.",
        "aired": "January 1, 1962",
        "mediatype": "episode"
      }
    },
    {
      "type": "item",
      "title": "S02E16 - Waxworks",
      "link": "https://archive.org/download/s-01-e-26-papa-benjamin/Thriller%20%281960%29%20-%20COMPLETE/S02E16%20-%20Waxworks.ia.mp4",
      "thumbnail": "https://media.themoviedb.org/t/p/w227_and_h127_face/oLITRDb9MxrHfSxAhR9wqbOjg2k.jpg",
      "fanart": "https://media.themoviedb.org/t/p/w1920_and_h800_multi_faces/4gFB4BF4zojCrD5JVHp74xWcoQL.jpg",
      "summary": "A traveling exhibit of wax figures of murderers seems to be the cause of some more recent deaths - are the wax figures real or is their creator a madman?",
      "content": "episode",
      "tvshowtitle": "Thriller",
      "season": "2",
      "episode": "16",
      "year": "1962",
      "infolabels": {
        "title": "Waxworks",
        "tvshowtitle": "Thriller",
        "season": 2,
        "episode": 16,
        "plot": "A traveling exhibit of wax figures of murderers seems to be the cause of some more recent deaths - are the wax figures real or is their creator a madman?",
        "aired": "January 8, 1962",
        "mediatype": "episode"
      }
    },
    {
      "type": "item",
      "title": "S02E17 - La Strega",
      "link": "https://archive.org/download/s-01-e-26-papa-benjamin/Thriller%20%281960%29%20-%20COMPLETE/S02E17%20-%20La%20Strega.ia.mp4",
      "thumbnail": "https://media.themoviedb.org/t/p/w227_and_h127_face/kt5pE82UBddqVfBjoLiRgFudexH.jpg",
      "fanart": "https://media.themoviedb.org/t/p/w1920_and_h800_multi_faces/4gFB4BF4zojCrD5JVHp74xWcoQL.jpg",
      "summary": "A young woman accused of being a witch goes to her young lover for protection against both her accusers and her grandmother, who really is a witch.",
      "content": "episode",
      "tvshowtitle": "Thriller",
      "season": "2",
      "episode": "17",
      "year": "1962",
      "infolabels": {
        "title": "La Strega",
        "tvshowtitle": "Thriller",
        "season": 2,
        "episode": 17,
        "plot": "A young woman accused of being a witch goes to her young lover for protection against both her accusers and her grandmother, who really is a witch.",
        "aired": "January 15, 1962",
        "mediatype": "episode"
      }
    },
    {
      "type": "item",
      "title": "S02E18 - The Storm",
      "link": "https://archive.org/download/s-01-e-26-papa-benjamin/Thriller%20%281960%29%20-%20COMPLETE/S02E18%20-%20The%20Storm.ia.mp4",
      "thumbnail": "https://media.themoviedb.org/t/p/w227_and_h127_face/9wVVotFAfjcT16OesCSdyqjPBqG.jpg",
      "fanart": "https://media.themoviedb.org/t/p/w1920_and_h800_multi_faces/4gFB4BF4zojCrD5JVHp74xWcoQL.jpg",
      "summary": "A woman returns home after two weeks and must spend the evening by herself during a raging storm. She is terrorized by strange sounds and the feeling she is not alone.",
      "content": "episode",
      "tvshowtitle": "Thriller",
      "season": "2",
      "episode": "18",
      "year": "1962",
      "infolabels": {
        "title": "The Storm",
        "tvshowtitle": "Thriller",
        "season": 2,
        "episode": 18,
        "plot": "A woman returns home after two weeks and must spend the evening by herself during a raging storm. She is terrorized by strange sounds and the feeling she is not alone.",
        "aired": "January 22, 1962",
        "mediatype": "episode"
      }
    },
    {
      "type": "item",
      "title": "S02E19 - A Wig For Miss Devore",
      "link": "https://archive.org/download/s-01-e-26-papa-benjamin/Thriller%20%281960%29%20-%20COMPLETE/S02E19%20-%20A%20Wig%20for%20Miss%20Devore.ia.mp4",
      "thumbnail": "https://media.themoviedb.org/t/p/w227_and_h127_face/xguHonLSpqtj2oQNKL9WKAl98FR.jpg",
      "fanart": "https://media.themoviedb.org/t/p/w1920_and_h800_multi_faces/4gFB4BF4zojCrD5JVHp74xWcoQL.jpg",
      "summary": "A washed-up actress selects for her comeback vehicle the story of a real woman who was accused of being a witch and susequently hanged. When she purchases the actual wig owned by the real woman an odd change occurs in the actress. It seems the wig holds a strange and hideous power.",
      "content": "episode",
      "tvshowtitle": "Thriller",
      "season": "2",
      "episode": "19",
      "year": "1962",
      "infolabels": {
        "title": "A Wig For Miss Devore",
        "tvshowtitle": "Thriller",
        "season": 2,
        "episode": 19,
        "plot": "A washed-up actress selects for her comeback vehicle the story of a real woman who was accused of being a witch and susequently hanged. When she purchases the actual wig owned by the real woman an odd change occurs in the actress. It seems the wig holds a strange and hideous power.",
        "aired": "January 29, 1962",
        "mediatype": "episode"
      }
    },
    {
      "type": "item",
      "title": "S02E20 - The Hollow Watcher",
      "link": "https://archive.org/download/s-01-e-26-papa-benjamin/Thriller%20%281960%29%20-%20COMPLETE/S02E20%20-%20The%20Hollow%20Watcher.ia.mp4",
      "thumbnail": "https://media.themoviedb.org/t/p/w227_and_h127_face/osz80WPRe42PPL1AkUwLDBIaziY.jpg",
      "fanart": "https://media.themoviedb.org/t/p/w1920_and_h800_multi_faces/4gFB4BF4zojCrD5JVHp74xWcoQL.jpg",
      "summary": "A scheming wife who murders her father-in-law is tormented by a strange being, a scarecrow.",
      "content": "episode",
      "tvshowtitle": "Thriller",
      "season": "2",
      "episode": "20",
      "year": "1962",
      "infolabels": {
        "title": "The Hollow Watcher",
        "tvshowtitle": "Thriller",
        "season": 2,
        "episode": 20,
        "plot": "A scheming wife who murders her father-in-law is tormented by a strange being, a scarecrow.",
        "aired": "February 12, 1962",
        "mediatype": "episode"
      }
    },
    {
      "type": "item",
      "title": "S02E21 - Cousin Tundifer",
      "link": "https://archive.org/download/s-01-e-26-papa-benjamin/Thriller%20%281960%29%20-%20COMPLETE/S02E21%20-%20Cousin%20Tundifer.ia.mp4",
      "thumbnail": "https://media.themoviedb.org/t/p/w227_and_h127_face/jhjzRSt7y1cOSglwm9lpegj2ZU9.jpg",
      "fanart": "https://media.themoviedb.org/t/p/w1920_and_h800_multi_faces/4gFB4BF4zojCrD5JVHp74xWcoQL.jpg",
      "summary": "A man tries to dispose of his uncle's body in a strange house that goes back in time everytime he sets foot in the living room.",
      "content": "episode",
      "tvshowtitle": "Thriller",
      "season": "2",
      "episode": "21",
      "year": "1962",
      "infolabels": {
        "title": "Cousin Tundifer",
        "tvshowtitle": "Thriller",
        "season": 2,
        "episode": 21,
        "plot": "A man tries to dispose of his uncle's body in a strange house that goes back in time everytime he sets foot in the living room.",
        "aired": "February 19, 1962",
        "mediatype": "episode"
      }
    },
    {
      "type": "item",
      "title": "S02E22 - The Incredible Doktor Markesan",
      "link": "https://archive.org/download/s-01-e-26-papa-benjamin/Thriller%20%281960%29%20-%20COMPLETE/S02E22%20-%20The%20Incredible%20Doktor%20Markesan.ia.mp4",
      "thumbnail": "https://media.themoviedb.org/t/p/w227_and_h127_face/jMQt9moLdtgm0EDOJhVFZWrtIUs.jpg",
      "fanart": "https://media.themoviedb.org/t/p/w1920_and_h800_multi_faces/4gFB4BF4zojCrD5JVHp74xWcoQL.jpg",
      "summary": "A young couple go to stay with an uncle while they look for work in a new town. They find the house run-down and their visit unexpected. Locked in their room at night they become curious about the goings-on in the house, but they could never imagine the true horror of their uncle's nocturnal activities.",
      "content": "episode",
      "tvshowtitle": "Thriller",
      "season": "2",
      "episode": "22",
      "year": "1962",
      "infolabels": {
        "title": "The Incredible Doktor Markesan",
        "tvshowtitle": "Thriller",
        "season": 2,
        "episode": 22,
        "plot": "A young couple go to stay with an uncle while they look for work in a new town. They find the house run-down and their visit unexpected. Locked in their room at night they become curious about the goings-on in the house, but they could never imagine the true horror of their uncle's nocturnal activities.",
        "aired": "February 26, 1962",
        "mediatype": "episode"
      }
    },
    {
      "type": "item",
      "title": "S02E23 - Flowers of Evil",
      "link": "https://archive.org/download/s-01-e-26-papa-benjamin/Thriller%20%281960%29%20-%20COMPLETE/S02E23%20-%20Flowers%20of%20Evil.ia.mp4",
      "thumbnail": "https://media.themoviedb.org/t/p/w227_and_h127_face/pWfjcpBJxg2Y9NQgQhbQgIy5uuX.jpg",
      "fanart": "https://media.themoviedb.org/t/p/w1920_and_h800_multi_faces/4gFB4BF4zojCrD5JVHp74xWcoQL.jpg",
      "summary": "The skeleton of a man seems much more alive than those responsible for his death had hoped - it laughs, screams and even moves!",
      "content": "episode",
      "tvshowtitle": "Thriller",
      "season": "2",
      "episode": "23",
      "year": "1962",
      "infolabels": {
        "title": "Flowers of Evil",
        "tvshowtitle": "Thriller",
        "season": 2,
        "episode": 23,
        "plot": "The skeleton of a man seems much more alive than those responsible for his death had hoped - it laughs, screams and even moves!",
        "aired": "March 5, 1962",
        "mediatype": "episode"
      }
    },
    {
      "type": "item",
      "title": "S02E24 - 'Til Death Do Us Part",
      "link": "https://archive.org/download/s-01-e-26-papa-benjamin/Thriller%20%281960%29%20-%20COMPLETE/S02E24%20-%20%27Til%20Death%20Do%20Us%20Part.ia.mp4",
      "thumbnail": "https://media.themoviedb.org/t/p/w227_and_h127_face/km9jZ8R8FVDC5ZePpq4AQLBMHf6.jpg",
      "fanart": "https://media.themoviedb.org/t/p/w1920_and_h800_multi_faces/4gFB4BF4zojCrD5JVHp74xWcoQL.jpg",
      "summary": "A henpecked undertaker disposes of his wife along with one of his customers then moves on to a new town and a new wife. But this one won't be so easy to get rid of.",
      "content": "episode",
      "tvshowtitle": "Thriller",
      "season": "2",
      "episode": "24",
      "year": "1962",
      "infolabels": {
        "title": "'Til Death Do Us Part",
        "tvshowtitle": "Thriller",
        "season": 2,
        "episode": 24,
        "plot": "A henpecked undertaker disposes of his wife along with one of his customers then moves on to a new town and a new wife. But this one won't be so easy to get rid of.",
        "aired": "March 12, 1962",
        "mediatype": "episode"
      }
    },
    {
      "type": "item",
      "title": "S02E25 - The Bride Who Died Twice",
      "link": "https://archive.org/download/s-01-e-26-papa-benjamin/Thriller%20%281960%29%20-%20COMPLETE/S02E25%20-%20The%20Bride%20Who%20Died%20Twice.ia.mp4",
      "thumbnail": "https://media.themoviedb.org/t/p/w227_and_h127_face/Po80kq8RPSoLRjq90JHOSO5tcQ.jpg",
      "fanart": "https://media.themoviedb.org/t/p/w1920_and_h800_multi_faces/4gFB4BF4zojCrD5JVHp74xWcoQL.jpg",
      "summary": "A general is forced to give his daughter's hand in marriage to his corrupt commanding officer but the marriage only results in her death.",
      "content": "episode",
      "tvshowtitle": "Thriller",
      "season": "2",
      "episode": "25",
      "year": "1962",
      "infolabels": {
        "title": "The Bride Who Died Twice",
        "tvshowtitle": "Thriller",
        "season": 2,
        "episode": 25,
        "plot": "A general is forced to give his daughter's hand in marriage to his corrupt commanding officer but the marriage only results in her death.",
        "aired": "March 19, 1962",
        "mediatype": "episode"
      }
    },
    {
      "type": "item",
      "title": "S02E26 - Kill My Love",
      "link": "https://archive.org/download/s-01-e-26-papa-benjamin/Thriller%20%281960%29%20-%20COMPLETE/S02E26%20-%20Kill%20My%20Love.ia.mp4",
      "thumbnail": "https://media.themoviedb.org/t/p/w227_and_h127_face/usEa4xjjRDUtaJocew46CG6qW5n.jpg",
      "fanart": "https://media.themoviedb.org/t/p/w1920_and_h800_multi_faces/4gFB4BF4zojCrD5JVHp74xWcoQL.jpg",
      "summary": "An adulterer tries to remove every obstacle in his life by way of murder - will his son be another victim?",
      "content": "episode",
      "tvshowtitle": "Thriller",
      "season": "2",
      "episode": "26",
      "year": "1962",
      "infolabels": {
        "title": "Kill My Love",
        "tvshowtitle": "Thriller",
        "season": 2,
        "episode": 26,
        "plot": "An adulterer tries to remove every obstacle in his life by way of murder - will his son be another victim?",
        "aired": "March 26, 1962",
        "mediatype": "episode"
      }
    },
    {
      "type": "item",
      "title": "S02E27 - Man of Mystery",
      "link": "https://archive.org/download/s-01-e-26-papa-benjamin/Thriller%20%281960%29%20-%20COMPLETE/S02E27%20-%20Man%20of%20Mystery.ia.mp4",
      "thumbnail": "https://media.themoviedb.org/t/p/w227_and_h127_face/dp5e3R6XwDaYLj6lnX3Lr81igw1.jpg",
      "fanart": "https://media.themoviedb.org/t/p/w1920_and_h800_multi_faces/4gFB4BF4zojCrD5JVHp74xWcoQL.jpg",
      "summary": "A mysterious and powerful man is keeping many secrets and everytime someone gets close to the truth, they are murdered. Will a beautiful young singer survive her relationship with the man of mystery?",
      "content": "episode",
      "tvshowtitle": "Thriller",
      "season": "2",
      "episode": "27",
      "year": "1962",
      "infolabels": {
        "title": "Man of Mystery",
        "tvshowtitle": "Thriller",
        "season": 2,
        "episode": 27,
        "plot": "A mysterious and powerful man is keeping many secrets and everytime someone gets close to the truth, they are murdered. Will a beautiful young singer survive her relationship with the man of mystery?",
        "aired": "April 2, 1962",
        "mediatype": "episode"
      }
    },
    {
      "type": "item",
      "title": "S02E28 - The Innocent Bystanders",
      "link": "https://archive.org/download/s-01-e-26-papa-benjamin/Thriller%20%281960%29%20-%20COMPLETE/S02E28%20-%20The%20Innocent%20Bystanders.ia.mp4",
      "thumbnail": "https://media.themoviedb.org/t/p/w227_and_h127_face/oVnTD54Pbkkd0AaGseiaDy9alDh.jpg",
      "fanart": "https://media.themoviedb.org/t/p/w1920_and_h800_multi_faces/4gFB4BF4zojCrD5JVHp74xWcoQL.jpg",
      "summary": "A pair of nineteenth centure body snatchers take their business too far by murdering innocent bystanders to further their profits.",
      "content": "episode",
      "tvshowtitle": "Thriller",
      "season": "2",
      "episode": "28",
      "year": "1962",
      "infolabels": {
        "title": "The Innocent Bystanders",
        "tvshowtitle": "Thriller",
        "season": 2,
        "episode": 28,
        "plot": "A pair of nineteenth centure body snatchers take their business too far by murdering innocent bystanders to further their profits.",
        "aired": "April 9, 1962",
        "mediatype": "episode"
      }
    },
    {
      "type": "item",
      "title": "S02E29 - The Lethal Ladies",
      "link": "https://archive.org/download/s-01-e-26-papa-benjamin/Thriller%20%281960%29%20-%20COMPLETE/S02E29%20-%20The%20Lethal%20Ladies.ia.mp4",
      "thumbnail": "https://media.themoviedb.org/t/p/w227_and_h127_face/AsA1wrfaXGkKKbr5ceuCb514QRv.jpg",
      "fanart": "https://media.themoviedb.org/t/p/w1920_and_h800_multi_faces/4gFB4BF4zojCrD5JVHp74xWcoQL.jpg",
      "summary": "Two separate tales: a woman deals with her unfaithful husband; a mousy librarian takes revenge on her tyrannical boss.",
      "content": "episode",
      "tvshowtitle": "Thriller",
      "season": "2",
      "episode": "29",
      "year": "1962",
      "infolabels": {
        "title": "The Lethal Ladies",
        "tvshowtitle": "Thriller",
        "season": 2,
        "episode": 29,
        "plot": "Two separate tales: a woman deals with her unfaithful husband; a mousy librarian takes revenge on her tyrannical boss.",
        "aired": "April 16, 1962",
        "mediatype": "episode"
      }
    },
    {
      "type": "item",
      "title": "S02E30 - The Specialists",
      "link": "https://archive.org/download/s-01-e-26-papa-benjamin/Thriller%20%281960%29%20-%20COMPLETE/S02E30%20-%20The%20Specialists.ia.mp4",
      "thumbnail": "https://media.themoviedb.org/t/p/w227_and_h127_face/jyc9J4HnFRJbijfiZwQmjeS05d1.jpg",
      "fanart": "https://media.themoviedb.org/t/p/w1920_and_h800_multi_faces/4gFB4BF4zojCrD5JVHp74xWcoQL.jpg",
      "summary": "A group of special detectives try to capture international jewel thieves and save the life of an innocent young woman who has become entangled in their web.",
      "content": "episode",
      "tvshowtitle": "Thriller",
      "season": "2",
      "episode": "30",
      "year": "1962",
      "infolabels": {
        "title": "The Specialists",
        "tvshowtitle": "Thriller",
        "season": 2,
        "episode": 30,
        "plot": "A group of special detectives try to capture international jewel thieves and save the life of an innocent young woman who has become entangled in their web.",
        "aired": "April 30, 1962",
        "mediatype": "episode"
      }
    }
  ]
}